Workbook
Name Utsnitt_ACG_casemix: #N/A
Name Utsnitt_Antal_listade_pat: #N/A
Name Utsnitt_Intäkter___listad_pat: #N/A
Name Utsnitt_Medical_staff_cost___listad_pat: #N/A
Name Utsnitt_Other_direct_costs___listad_pat: #N/A
Name Utsnitt_Stor_GBG_AO: #N/A

Sheet Resultat-VC (3)
A1: Source.Name | B1: CG Item | C1: Column2 | D1: Column3 | E1: Selected Period | F1: Selected Period_1 | G1: Selected Period_2 | H1: Selected Period_3 | I1: Selected Period_4 | J1: Selected Period_5 | K1: Selected Period_6 | L1: Selected Period_7 | M1: Selected Period_8 | N1: Selected Period_9 | O1: Selected Period_10 | P1: Selected Period_11 | Q1: Selected Period_12 | R1: Selected Period_13 | S1: Selected Period_14 | T1: Selected Period_15 | U1: Selected Period_16 | V1: Selected Period_17 | W1: Selected Period_18 | X1: Selected Period_19 | Y1: Selected Period_20 | Z1: Selected Period_21 | AA1: Selected Period_22 | AB1: Selected Period_23 | AC1: Selected Period_24 | AD1: Selected Period_25
A2: 015.xlsx | B2: Year Month No | E2: 202312 | F2: 202401 | G2: 202402 | H2: 202403 | I2: 202404 | J2: 202405 | K2: 202406 | L2: 202407 | M2: 202408 | N2: 202409 | O2: 202410 | P2: 202411 | Q2: 202412 | R2: 202501 | S2: 202502 | T2: 202503 | U2: 202504 | V2: 202505 | W2: 202506 | X2: 202507 | Y2: 202508 | Z2: 202509 | AA2: 202510 | AB2: 202511 | AC2: 202512 | AD2: 202601
A3: 015.xlsx | B3: Scenario | E3: Actual | F3: Actual | G3: Actual | H3: Actual | I3: Actual | J3: Actual | K3: Actual | L3: Actual | M3: Actual | N3: Actual | O3: Actual | P3: Actual | Q3: Actual | R3: Actual | S3: Actual | T3: Actual | U3: Actual | V3: Actual | W3: Actual | X3: Actual | Y3: Actual | Z3: Actual | AA3: Actual | AB3: Actual | AC3: Actual | AD3: Actual
A4: 015.xlsx | B4: ElementName | C4: Reference Account | D4: Cluster | E4: Profit and Loss Table | F4: Profit and Loss Table | G4: Profit and Loss Table | H4: Profit and Loss Table | I4: Profit and Loss Table | J4: Profit and Loss Table | K4: Profit and Loss Table | L4: Profit and Loss Table | M4: Profit and Loss Table | N4: Profit and Loss Table | O4: Profit and Loss Table | P4: Profit and Loss Table | Q4: Profit and Loss Table | R4: Profit and Loss Table | S4: Profit and Loss Table | T4: Profit and Loss Table | U4: Profit and Loss Table | V4: Profit and Loss Table | W4: Profit and Loss Table | X4: Profit and Loss Table | Y4: Profit and Loss Table | Z4: Profit and Loss Table | AA4: Profit and Loss Table | AB4: Profit and Loss Table | AC4: Profit and Loss Table | AD4: Profit and Loss Table
A5: 015.xlsx | B5: Revenue | C5: Total | L5: 17900 | M5: -0.5 | N5: 49657.22 | O5: 134821.97 | P5: 191819.63 | Q5: 174736.02 | R5: 231650.33 | S5: 230589.78 | T5: 256219.36 | U5: 274278.18 | V5: 270523.18 | W5: 329856.16 | X5: 373500.85 | Y5: 390490.68 | Z5: 406486.25 | AA5: 433006.53 | AB5: 569810.34 | AC5: 540626.52 | AD5: 540246.35
A6: 015.xlsx | B6: Revenue | C6: Revenues | D6: Total | N6: 49657.22 | O6: 103571.97 | P6: 160069.63 | Q6: 158485.96 | R6: 202669.33 | S6: 229839.78 | T6: 254769.36 | U6: 274278.18 | V6: 270523.18 | W6: 329856.16 | X6: 373500.85 | Y6: 389990.68 | Z6: 406736.25 | AA6: 432042.53 | AB6: 569809.84 | AC6: 539564.02 | AD6: 537543.24
A7: 015.xlsx | B7: Revenue | C7: Revenues | D7: RG Huvudintäkter | N7: 42957.22 | O7: 87371.97 | P7: 149764.63 | Q7: 157005.96 | R7: 202669.33 | S7: 224834.78 | T7: 248373.36 | U7: 275498.18 | V7: 275498.18 | W7: 330771.16 | X7: 333083.85 | Y7: 381700.68 | Z7: 395221.25 | AA7: 407547.53 | AB7: 476681.84 | AC7: 525489.02 | AD7: 520984.24
A8: 015.xlsx | B8: Revenue | C8: Revenues | D8: Patientintäkter | N8: 6700 | O8: 16200 | P8: 10305 | Q8: 1480 | R8: 0 | S8: 5005 | T8: 6396 | U8: -1220 | V8: -4975 | W8: -915 | X8: 40417 | Y8: 8290 | Z8: 11515 | AA8: 24495 | AB8: 28180 | AC8: 14075 | AD8: 16559
A9: 015.xlsx | B9: Revenue | C9: Revenues | D9: Övriga intäkter | AB9: 64948
A10: 015.xlsx | B10: Revenue | C10: Other revenues | D10: Total | L10: 17900 | M10: -0.5 | O10: 31250 | P10: 31750 | Q10: 16250.06 | R10: 28981 | S10: 750 | T10: 1450 | Y10: 500 | Z10: -250 | AA10: 964 | AB10: 0.5 | AC10: 1062.5 | AD10: 2703.11
A11: 015.xlsx | B11: COGS | C11: Total | I11: -90679.8 | J11: -101126.21 | K11: -99615.21 | L11: -100860.21 | M11: -176307.24 | N11: -670610.11 | O11: -730350.46 | P11: -860951.32 | Q11: -1046134.9 | R11: -760570 | S11: -721653.37 | T11: -647256.52 | U11: -748203.19 | V11: -699197.42 | W11: -846891.93 | X11: -742923.78 | Y11: -806606.7 | Z11: -683240.2 | AA11: -779287.23 | AB11: -670913.99 | AC11: -646508.28 | AD11: -702478.73
A12: 015.xlsx | B12: COGS | C12: Medical staff | D12: Total | I12: -90679.8 | J12: -101126.21 | K12: -99615.21 | L12: -100860.21 | M12: -176307.24 | N12: -587574.45 | O12: -631054.06 | P12: -792145.81 | Q12: -1001478.6 | R12: -635308.02 | S12: -644869.24 | T12: -469462.36 | U12: -770294.22 | V12: -606283.24 | W12: -749676.94 | X12: -648318.2 | Y12: -735801.19 | Z12: -558198.34 | AA12: -659107.97 | AB12: -523949.07 | AC12: -518894.56 | AD12: -548991.86
A13: 015.xlsx | B13: COGS | C13: Other direct costs | D13: Total | L13: 0 | M13: 0 | N13: -83035.66 | O13: -99296.4 | P13: -68805.51 | Q13: -44656.31 | R13: -125261.98 | S13: -76784.13 | T13: -177794.16 | U13: 22091.03 | V13: -92914.18 | W13: -97214.99 | X13: -94605.58 | Y13: -70805.51 | Z13: -125041.86 | AA13: -120179.26 | AB13: -146964.92 | AC13: -127613.72 | AD13: -153486.87
A14: 015.xlsx | B14: Gross Profit | C14: Total | I14: -90679.8 | J14: -101126.21 | K14: -99615.21 | L14: -82960.21 | M14: -176307.74 | N14: -620952.89 | O14: -595528.49 | P14: -669131.69 | Q14: -871398.9 | R14: -528919.67 | S14: -491063.59 | T14: -391037.16 | U14: -473925.01 | V14: -428674.24 | W14: -517035.77 | X14: -369422.93 | Y14: -416116.02 | Z14: -276753.95 | AA14: -346280.7 | AB14: -101103.65 | AC14: -105881.76 | AD14: -162232.38
A15: 015.xlsx | B15: OPEX | C15: Total | F15: 0 | G15: 0 | H15: 36 | I15: 2771.16 | J15: -6605 | K15: -4966.17 | L15: -72402.87 | M15: 0 | N15: -739493.87 | O15: -515692.41 | P15: -270226.33 | Q15: -354261.63 | R15: -370328.32 | S15: -397390.89 | T15: -378383.51 | U15: -326828.4 | V15: -375946.74 | W15: -407136.25 | X15: -335336.29 | Y15: -349598.39 | Z15: -288249.93 | AA15: -242432.78 | AB15: -280032.5 | AC15: -250202.84 | AD15: -259066.8
A16: 015.xlsx | B16: OPEX | C16: Operating expenses | D16: Total | F16: 0 | G16: 0 | H16: 36 | I16: 2771.16 | J16: -6605 | K16: -4966.17 | L16: -72402.87 | M16: 0 | N16: -612869.53 | O16: -443080.07 | P16: -243817.99 | Q16: -319963.13 | R16: -355467.98 | S16: -382982.55 | T16: -363975.17 | U16: -312420.06 | V16: -361538.4 | W16: -392727.91 | X16: -320927.95 | Y16: -326180.13 | Z16: -287269.93 | AA16: -249858.58 | AB16: -284637.73 | AC16: -257089.93 | AD16: -246358.03
A17: 015.xlsx | B17: OPEX | C17: Overhead costs | D17: Total | K17: 0 | L17: 0 | N17: -126624.34 | O17: -72612.34 | P17: -26408.34 | Q17: -34298.5 | R17: -14860.34 | S17: -14408.34 | T17: -14408.34 | U17: -14408.34 | V17: -14408.34 | W17: -14408.34 | X17: -14408.34 | Y17: -23418.26 | Z17: -980 | AA17: 7425.8 | AB17: 4605.23 | AC17: 6887.09 | AD17: -12708.77
A18: 015.xlsx | B18: EBITDA1 | C18: Total | F18: 0 | G18: 0 | H18: 36 | I18: -87908.64 | J18: -107731.21 | K18: -104581.38 | L18: -155363.08 | M18: -176307.74 | N18: -1360446.8 | O18: -1111220.9 | P18: -939358.02 | Q18: -1225660.5 | R18: -899247.99 | S18: -888454.48 | T18: -769420.67 | U18: -800753.41 | V18: -804620.98 | W18: -924172.02 | X18: -704759.22 | Y18: -765714.41 | Z18: -565003.88 | AA18: -588713.48 | AB18: -381136.15 | AC18: -356084.6 | AD18: -421299.18
A19: 015.xlsx | B19: EBITDA2 | C19: Total | F19: 0 | G19: 0 | H19: 36 | I19: -87908.64 | J19: -107731.21 | K19: -104581.38 | L19: -155363.08 | M19: -176307.74 | N19: -1360446.8 | O19: -1111220.9 | P19: -939358.02 | Q19: -1225660.5 | R19: -899247.99 | S19: -888454.48 | T19: -769420.67 | U19: -800753.41 | V19: -804620.98 | W19: -924172.02 | X19: -704759.22 | Y19: -765714.41 | Z19: -565003.88 | AA19: -588713.48 | AB19: -381136.15 | AC19: -356084.6 | AD19: -421299.18
A20: 015.xlsx | B20: Adjustments historical | C20: Total | E20: 0 | F20: 0 | G20: 0 | H20: 0 | I20: 0 | J20: 0 | K20: 0 | L20: 0 | M20: 0 | N20: 0 | O20: 0 | P20: 0 | Q20: 0 | R20: 0 | S20: 0 | T20: 0 | U20: 0 | V20: 0 | W20: 0 | X20: 0 | Y20: 0 | Z20: 0 | AA20: 0 | AB20: 0 | AC20: 0 | AD20: 0
A21: 015.xlsx | B21: EBITDA2 (adjusted) | C21: Total | E21: 0 | F21: 0 | G21: 0 | H21: 36 | I21: -87908.64 | J21: -107731.21 | K21: -104581.38 | L21: -155363.08 | M21: -176307.74 | N21: -1360446.8 | O21: -1111220.9 | P21: -939358.02 | Q21: -1225660.5 | R21: -899247.99 | S21: -888454.48 | T21: -769420.67 | U21: -800753.41 | V21: -804620.98 | W21: -924172.02 | X21: -704759.22 | Y21: -765714.41 | Z21: -565003.88 | AA21: -588713.48 | AB21: -381136.15 | AC21: -356084.6 | AD21: -421299.18
A22: 015.xlsx | B22: Depreciation & Amortisation | C22: Total | O22: -8313 | P22: -8313 | Q22: -8313 | R22: -8313 | S22: -8313 | T22: -7759 | U22: -8868 | V22: -9145 | W22: -8298 | X22: -8297 | Y22: -8298 | Z22: -8297 | AA22: -8298 | AB22: -8297 | AC22: -8298 | AD22: -8297
A23: 015.xlsx | B23: Financial Items | C23: Total | J23: -66.79 | O23: -275
A24: 015.xlsx | B24: Total | C24: Total | F24: 0 | G24: 0 | H24: 36 | I24: -87908.64 | J24: -107798 | K24: -104581.38 | L24: -155363.08 | M24: -176307.74 | N24: -1360446.8 | O24: -1119808.9 | P24: -947671.02 | Q24: -1233973.5 | R24: -907560.99 | S24: -896767.48 | T24: -777179.67 | U24: -809621.41 | V24: -813765.98 | W24: -932470.02 | X24: -713056.22 | Y24: -774012.41 | Z24: -573300.88 | AA24: -597011.48 | AB24: -389433.15 | AC24: -364382.6 | AD24: -429596.18
A25: 015.xlsx | B25: Total
A26: 015.xlsx
A27: 015.xlsx | B27: Tillämpade filter: CG Item är Selected Period Scenario är inte N/A Value är SEK Inkluderade (4) 2024 (Year), 2025 (Year), 2026 (Year) + January (Month), 2023 (Year) + December (Month) Inkluderade (1) VC VGR (Cost Center Type) + VC StorGöteborg (Business Area) + 015 Karlastaden (Name) Scenario är Actual
A28: 102.xlsx | B28: Year Month No | E28: 202312 | F28: 202401 | G28: 202402 | H28: 202403 | I28: 202404 | J28: 202405 | K28: 202406 | L28: 202407 | M28: 202408 | N28: 202409 | O28: 202410 | P28: 202411 | Q28: 202412 | R28: 202501 | S28: 202502 | T28: 202503 | U28: 202504 | V28: 202505 | W28: 202506 | X28: 202507 | Y28: 202508 | Z28: 202509 | AA28: 202510 | AB28: 202511 | AC28: 202512 | AD28: 202601
A29: 102.xlsx | B29: Scenario | E29: Actual | F29: Actual | G29: Actual | H29: Actual | I29: Actual | J29: Actual | K29: Actual | L29: Actual | M29: Actual | N29: Actual | O29: Actual | P29: Actual | Q29: Actual | R29: Actual | S29: Actual | T29: Actual | U29: Actual | V29: Actual | W29: Actual | X29: Actual | Y29: Actual | Z29: Actual | AA29: Actual | AB29: Actual | AC29: Actual | AD29: Actual
A30: 102.xlsx | B30: ElementName | C30: Reference Account | D30: Cluster | E30: Profit and Loss Table | F30: Profit and Loss Table | G30: Profit and Loss Table | H30: Profit and Loss Table | I30: Profit and Loss Table | J30: Profit and Loss Table | K30: Profit and Loss Table | L30: Profit and Loss Table | M30: Profit and Loss Table | N30: Profit and Loss Table | O30: Profit and Loss Table | P30: Profit and Loss Table | Q30: Profit and Loss Table | R30: Profit and Loss Table | S30: Profit and Loss Table | T30: Profit and Loss Table | U30: Profit and Loss Table | V30: Profit and Loss Table | W30: Profit and Loss Table | X30: Profit and Loss Table | Y30: Profit and Loss Table | Z30: Profit and Loss Table | AA30: Profit and Loss Table | AB30: Profit and Loss Table | AC30: Profit and Loss Table | AD30: Profit and Loss Table
A31: 102.xlsx | B31: Revenue | C31: Total | E31: 3539425.8 | F31: 3373216.1 | G31: 3529393.2 | H31: 3533690.3 | I31: 3544853.9 | J31: 3575957.9 | K31: 3492686.3 | L31: 3420694.5 | M31: 3488483.1 | N31: 3710206.4 | O31: 3313629.2 | P31: 3688494.1 | Q31: 3635877.7 | R31: 3670720.6 | S31: 3645688 | T31: 3806362.2 | U31: 3722878.2 | V31: 3756390.2 | W31: 3604808 | X31: 3535541.6 | Y31: 3496710.3 | Z31: 3711019.5 | AA31: 3716153.6 | AB31: 3613652.5 | AC31: 3796178.7 | AD31: 3430029.6
A32: 102.xlsx | B32: Revenue | C32: Revenues | D32: Total | E32: 3487134.3 | F32: 3282060.1 | G32: 3265822.8 | H32: 3370051.3 | I32: 3380354.9 | J32: 3331807.9 | K32: 3325656.3 | L32: 3306954.5 | M32: 3266033.1 | N32: 3476416.9 | O32: 3140180 | P32: 3527794.1 | Q32: 3472382.7 | R32: 3531921.1 | S32: 3493617 | T32: 3583873.2 | U32: 3522200.6 | V32: 3547192.3 | W32: 3529817 | X32: 3484622.2 | Y32: 3432631.4 | Z32: 3538259.1 | AA32: 3489428.6 | AB32: 3506255.3 | AC32: 3688388.7 | AD32: 3342523.4
A33: 102.xlsx | B33: Revenue | C33: Revenues | D33: RG Huvudintäkter | E33: 3387788.5 | F33: 3257986.8 | G33: 3221008.8 | H33: 3302493.1 | I33: 3274832.3 | J33: 3270634.9 | K33: 3300053.1 | L33: 3298555.5 | M33: 3225088.1 | N33: 3426266.9 | O33: 3070676.5 | P33: 3484742.1 | Q33: 3390123 | R33: 3468679.8 | S33: 3499441.8 | T33: 3508258 | U33: 3505660.1 | V33: 3505660.1 | W33: 3483461 | X33: 3481113.6 | Y33: 3429516.4 | Z33: 3456283.5 | AA33: 3469460 | AB33: 3494373.3 | AC33: 3575214.2 | AD33: 3339426.4
A34: 102.xlsx | B34: Revenue | C34: Revenues | D34: Patientintäkter | E34: 63472.83 | F34: 19817.23 | G34: 31049 | H34: 17942.21 | I34: 81305.64 | J34: 12586 | K34: 0.2 | L34: 2775 | M34: 33340 | N34: 42860 | O34: 25662.55 | P34: 3195 | Q34: 34353.7 | R34: 45944.77 | T34: 42104.42 | U34: 10921.9 | V34: 20147.97 | W34: 12403.29 | Z34: 74895.66 | AA34: 14616.61 | AC34: 25998.48
A35: 102.xlsx | B35: Revenue | C35: Revenues | D35: Övriga intäkter | E35: 35873 | F35: 4256 | G35: 13765 | H35: 49616 | I35: 24217 | J35: 48587 | K35: 25603 | L35: 5624 | M35: 7605 | N35: 7290 | O35: 43841 | P35: 39857 | Q35: 47906 | R35: 17296.6 | S35: -5824.8 | T35: 33510.8 | U35: 5618.6 | V35: 21384.2 | W35: 33952.8 | X35: 3508.6 | Y35: 3115 | Z35: 7080 | AA35: 5352 | AB35: 11882 | AC35: 87176 | AD35: 3097
A36: 102.xlsx | B36: Revenue | C36: Other revenues | D36: Total | E36: 52291.5 | F36: 91156 | G36: 263570.5 | H36: 163639.04 | I36: 164499 | J36: 244150 | K36: 167029.95 | L36: 113740 | M36: 222450 | N36: 233789.55 | O36: 173449.21 | P36: 160700 | Q36: 163495.05 | R36: 138799.5 | S36: 152071 | T36: 222488.98 | U36: 200677.62 | V36: 209197.92 | W36: 74991 | X36: 50919.42 | Y36: 64078.84 | Z36: 172760.34 | AA36: 226725 | AB36: 107397.2 | AC36: 107790 | AD36: 87506.22
A37: 102.xlsx | B37: COGS | C37: Total | E37: -2652479.4 | F37: -2518425.9 | G37: -2614019.9 | H37: -2598007.8 | I37: -2775164 | J37: -2842492.1 | K37: -2739042.5 | L37: -2704049.9 | M37: -2754631.7 | N37: -3092039.1 | O37: -2799911.7 | P37: -2775437.5 | Q37: -2821468.3 | R37: -2650299.6 | S37: -2745698.6 | T37: -2724796.3 | U37: -2483183.2 | V37: -2483479 | W37: -2643545.9 | X37: -2543088.5 | Y37: -2539641.3 | Z37: -2633199.2 | AA37: -2701046.7 | AB37: -2474330.4 | AC37: -2660004 | AD37: -2462201.3
A38: 102.xlsx | B38: COGS | C38: Medical staff | D38: Total | E38: -1655124.9 | F38: -1620790.8 | G38: -1702474.1 | H38: -1588865.5 | I38: -1738137.5 | J38: -1844514.8 | K38: -1805177.3 | L38: -1840020.4 | M38: -1902602.4 | N38: -2083027.1 | O38: -1839555.1 | P38: -1841113.5 | Q38: -1966897.1 | R38: -1780154 | S38: -1870192.2 | T38: -1812623.7 | U38: -1585311.1 | V38: -1553251.9 | W38: -1608763.6 | X38: -1636803.4 | Y38: -1721765.3 | Z38: -1702511.7 | AA38: -1630892.8 | AB38: -1583895.1 | AC38: -1687174.7 | AD38: -1639769.8
A39: 102.xlsx | B39: COGS | C39: Other direct costs | D39: Total | E39: -997354.58 | F39: -897635.13 | G39: -911545.79 | H39: -1009142.3 | I39: -1037026.5 | J39: -997977.35 | K39: -933865.22 | L39: -864029.5 | M39: -852029.29 | N39: -1009012 | O39: -960356.63 | P39: -934324.02 | Q39: -854571.17 | R39: -870145.6 | S39: -875506.41 | T39: -912172.6 | U39: -897872.02 | V39: -930227.13 | W39: -1034782.3 | X39: -906285.13 | Y39: -817876.07 | Z39: -930687.45 | AA39: -1070153.9 | AB39: -890435.29 | AC39: -972829.35 | AD39: -822431.49
A40: 102.xlsx | B40: Gross Profit | C40: Total | E40: 886946.41 | F40: 854790.15 | G40: 915373.31 | H40: 935682.5 | I40: 769689.92 | J40: 733465.79 | K40: 753643.75 | L40: 716644.56 | M40: 733851.43 | N40: 618167.28 | O40: 513717.48 | P40: 913056.58 | Q40: 814409.43 | R40: 1020421 | S40: 899989.44 | T40: 1081565.9 | U40: 1239695.1 | V40: 1272911.2 | W40: 961262.18 | X40: 992453.12 | Y40: 957068.92 | Z40: 1077820.3 | AA40: 1015107 | AB40: 1139322.1 | AC40: 1136174.7 | AD40: 967828.26
A41: 102.xlsx | B41: OPEX | C41: Total | E41: -289720.3 | F41: -334747.93 | G41: -365919.8 | H41: -361395.79 | I41: -357053.78 | J41: -401281.29 | K41: -346643.02 | L41: -361497.32 | M41: -360487.99 | N41: -388653.81 | O41: -387976.07 | P41: -370361.62 | Q41: -548054.53 | R41: -327369.5 | S41: -391078.64 | T41: -375709.82 | U41: -395873.38 | V41: -405145.75 | W41: -390098.62 | X41: -365425.98 | Y41: -377197.6 | Z41: -413970.59 | AA41: -401730.35 | AB41: -446644.38 | AC41: -412919.04 | AD41: -379948.71
A42: 102.xlsx | B42: OPEX | C42: Operating expenses | D42: Total | E42: -237598.07 | F42: -299002.48 | G42: -325985.9 | H42: -324789.59 | I42: -320903.3 | J42: -365643.34 | K42: -310639.02 | L42: -323869.32 | M42: -324736.99 | N42: -345049.81 | O42: -344685.12 | P42: -333976.62 | Q42: -471485.89 | R42: -301791.34 | S42: -353174.65 | T42: -347734.82 | U42: -370395.15 | V42: -371123.92 | W42: -357963.08 | X42: -337970.36 | Y42: -348649.28 | Z42: -384430.04 | AA42: -373909.71 | AB42: -409844.42 | AC42: -375839.29 | AD42: -347586.99
A43: 102.xlsx | B43: OPEX | C43: Overhead costs | D43: Total | E43: -52122.23 | F43: -35745.45 | G43: -39933.9 | H43: -36606.2 | I43: -36150.48 | J43: -35637.95 | K43: -36004 | L43: -37628 | M43: -35751 | N43: -43604 | O43: -43290.95 | P43: -36385 | Q43: -76568.64 | R43: -25578.16 | S43: -37903.99 | T43: -27975 | U43: -25478.23 | V43: -34021.83 | W43: -32135.54 | X43: -27455.62 | Y43: -28548.32 | Z43: -29540.55 | AA43: -27820.64 | AB43: -36799.96 | AC43: -37079.75 | AD43: -32361.72
A44: 102.xlsx | B44: EBITDA1 | C44: Total | E44: 597226.11 | F44: 520042.22 | G44: 549453.51 | H44: 574286.71 | I44: 412636.14 | J44: 332184.5 | K44: 407000.73 | L44: 355147.24 | M44: 373363.44 | N44: 229513.47 | O44: 125741.41 | P44: 542694.96 | Q44: 266354.9 | R44: 693051.49 | S44: 508910.8 | T44: 705856.12 | U44: 843821.7 | V44: 867765.43 | W44: 571163.56 | X44: 627027.14 | Y44: 579871.32 | Z44: 663849.7 | AA44: 613376.61 | AB44: 692677.69 | AC44: 723255.63 | AD44: 587879.55
A45: 102.xlsx | B45: Management Fee/ Overhead | C45: Total | E45: -273513
A46: 102.xlsx | B46: Management Fee/ Overhead | C46: Management Fee | D46: Total | E46: -101414
A47: 102.xlsx | B47: Management Fee/ Overhead | C47: Service Fee | D47: Total | E47: -172099
A48: 102.xlsx | B48: EBITDA2 | C48: Total | E48: 323713.11 | F48: 520042.22 | G48: 549453.51 | H48: 574286.71 | I48: 412636.14 | J48: 332184.5 | K48: 407000.73 | L48: 355147.24 | M48: 373363.44 | N48: 229513.47 | O48: 125741.41 | P48: 542694.96 | Q48: 266354.9 | R48: 693051.49 | S48: 508910.8 | T48: 705856.12 | U48: 843821.7 | V48: 867765.43 | W48: 571163.56 | X48: 627027.14 | Y48: 579871.32 | Z48: 663849.7 | AA48: 613376.61 | AB48: 692677.69 | AC48: 723255.63 | AD48: 587879.55
A49: 102.xlsx | B49: Adjustments historical | C49: Total | E49: 0 | F49: 0 | G49: 0 | H49: 0 | I49: 0 | J49: 0 | K49: 0 | L49: 0 | M49: 0 | N49: 0 | O49: 0 | P49: 0 | Q49: 0 | R49: 0 | S49: 0 | T49: 0 | U49: 0 | V49: 0 | W49: 0 | X49: 0 | Y49: 0 | Z49: 0 | AA49: 0 | AB49: 0 | AC49: 0 | AD49: 0
A50: 102.xlsx | B50: EBITDA2 (adjusted) | C50: Total | E50: 323713.11 | F50: 520042.22 | G50: 549453.51 | H50: 574286.71 | I50: 412636.14 | J50: 332184.5 | K50: 407000.73 | L50: 355147.24 | M50: 373363.44 | N50: 229513.47 | O50: 125741.41 | P50: 542694.96 | Q50: 266354.9 | R50: 693051.49 | S50: 508910.8 | T50: 705856.12 | U50: 843821.7 | V50: 867765.43 | W50: 571163.56 | X50: 627027.14 | Y50: 579871.32 | Z50: 663849.7 | AA50: 613376.61 | AB50: 692677.69 | AC50: 723255.63 | AD50: 587879.55
A51: 102.xlsx | B51: Depreciation & Amortisation | C51: Total | E51: -4255 | F51: -6984 | G51: -6984 | H51: -6984 | I51: -6984 | J51: -6984 | K51: -6984 | L51: -6984 | M51: -6984 | N51: -6984 | O51: -6984 | P51: -6984 | Q51: -6984 | R51: -6984 | T51: -13967 | U51: -6984 | V51: -6984 | W51: -6984 | Y51: -13968 | Z51: -6984 | AA51: -6984 | AB51: -6984 | AC51: -6984 | AD51: -6984
A52: 102.xlsx | B52: Total | C52: Total | E52: 319458.11 | F52: 513058.22 | G52: 542469.51 | H52: 567302.71 | I52: 405652.14 | J52: 325200.5 | K52: 400016.73 | L52: 348163.24 | M52: 366379.44 | N52: 222529.47 | O52: 118757.41 | P52: 535710.96 | Q52: 259370.9 | R52: 686067.49 | S52: 508910.8 | T52: 691889.12 | U52: 836837.7 | V52: 860781.43 | W52: 564179.56 | X52: 627027.14 | Y52: 565903.32 | Z52: 656865.7 | AA52: 606392.61 | AB52: 685693.69 | AC52: 716271.63 | AD52: 580895.55
A53: 102.xlsx | B53: Total
A54: 102.xlsx
A55: 102.xlsx | B55: Tillämpade filter: CG Item är Selected Period Scenario är inte N/A Value är SEK Inkluderade (4) 2024 (Year), 2025 (Year), 2026 (Year) + January (Month), 2023 (Year) + December (Month) Inkluderade (1) VC VGR (Cost Center Type) + VC StorGöteborg (Business Area) + 102 Frölunda Torg (Name) Scenario är Actual
A56: 103.xlsx | B56: Year Month No | E56: 202312 | F56: 202401 | G56: 202402 | H56: 202403 | I56: 202404 | J56: 202405 | K56: 202406 | L56: 202407 | M56: 202408 | N56: 202409 | O56: 202410 | P56: 202411 | Q56: 202412 | R56: 202501 | S56: 202502 | T56: 202503 | U56: 202504 | V56: 202505 | W56: 202506 | X56: 202507 | Y56: 202508 | Z56: 202509 | AA56: 202510 | AB56: 202511 | AC56: 202512 | AD56: 202601
A57: 103.xlsx | B57: Scenario | E57: Actual | F57: Actual | G57: Actual | H57: Actual | I57: Actual | J57: Actual | K57: Actual | L57: Actual | M57: Actual | N57: Actual | O57: Actual | P57: Actual | Q57: Actual | R57: Actual | S57: Actual | T57: Actual | U57: Actual | V57: Actual | W57: Actual | X57: Actual | Y57: Actual | Z57: Actual | AA57: Actual | AB57: Actual | AC57: Actual | AD57: Actual
A58: 103.xlsx | B58: ElementName | C58: Reference Account | D58: Cluster | E58: Profit and Loss Table | F58: Profit and Loss Table | G58: Profit and Loss Table | H58: Profit and Loss Table | I58: Profit and Loss Table | J58: Profit and Loss Table | K58: Profit and Loss Table | L58: Profit and Loss Table | M58: Profit and Loss Table | N58: Profit and Loss Table | O58: Profit and Loss Table | P58: Profit and Loss Table | Q58: Profit and Loss Table | R58: Profit and Loss Table | S58: Profit and Loss Table | T58: Profit and Loss Table | U58: Profit and Loss Table | V58: Profit and Loss Table | W58: Profit and Loss Table | X58: Profit and Loss Table | Y58: Profit and Loss Table | Z58: Profit and Loss Table | AA58: Profit and Loss Table | AB58: Profit and Loss Table | AC58: Profit and Loss Table | AD58: Profit and Loss Table
A59: 103.xlsx | B59: Revenue | C59: Total | E59: 2904812.5 | F59: 2667093.6 | G59: 2666303.4 | H59: 2723625.6 | I59: 2764296.2 | J59: 2850896.5 | K59: 2746077.3 | L59: 2724928.6 | M59: 2706809.7 | N59: 2810090.2 | O59: 2776784.2 | P59: 2840902.9 | Q59: 2794952.9 | R59: 2905096.4 | S59: 2952572.2 | T59: 2987919 | U59: 3038822.6 | V59: 3031027 | W59: 3155943.7 | X59: 3113463.8 | Y59: 3131530.1 | Z59: 3251220.6 | AA59: 3102707 | AB59: 3164099.4 | AC59: 3425883.8 | AD59: 3042661.1
A60: 103.xlsx | B60: Revenue | C60: Revenues | D60: Total | E60: 2782803.5 | F60: 2558364.6 | G60: 2534131.4 | H60: 2607585.6 | I60: 2638758.2 | J60: 2684306.5 | K60: 2656297.8 | L60: 2614650.6 | M60: 2610002.7 | N60: 2589023.6 | O60: 2654925.5 | P60: 2730018.6 | Q60: 2638772.5 | R60: 2756276.4 | S60: 2803741.7 | T60: 2859819 | U60: 2903330.4 | V60: 2903025.6 | W60: 3027461.2 | X60: 2972352.8 | Y60: 2957811.1 | Z60: 3038139.6 | AA60: 2978753 | AB60: 2990862.4 | AC60: 3260034.8 | AD60: 2770168.8
A61: 103.xlsx | B61: Revenue | C61: Revenues | D61: RG Huvudintäkter | E61: 2665355.6 | F61: 2508673.7 | G61: 2481925.4 | H61: 2551115.3 | I61: 2500798.5 | J61: 2586789.5 | K61: 2585325.9 | L61: 2563245.6 | M61: 2537965.7 | N61: 2522402.6 | O61: 2571134.5 | P61: 2660875.6 | Q61: 2613482.2 | R61: 2704111.8 | S61: 2799509.5 | T61: 2809768.1 | U61: 2824575.4 | V61: 2824575.4 | W61: 2921849.5 | X61: 2908494.6 | Y61: 2893253 | Z61: 2839929.9 | AA61: 2840593 | AB61: 2900068.2 | AC61: 3005573.6 | AD61: 2682738.7
A62: 103.xlsx | B62: Revenue | C62: Revenues | D62: Patientintäkter | E62: 53844.88 | F62: 24304.84 | G62: 11725 | H62: 4357.34 | I62: 67968.76 | J62: 5590 | K62: -0.15 | L62: 0 | M62: 30395 | N62: 21385 | O62: 36401.99 | P62: 925 | Q62: 7971.31 | R62: 22086.57 | T62: 43140.27 | U62: 9396.82 | V62: 3751.67 | W62: 27138.32 | Z62: 111068.52 | AA62: 72590.85 | AD62: 20996
A63: 103.xlsx | B63: Revenue | C63: Revenues | D63: Övriga intäkter | E63: 63603 | F63: 25386 | G63: 40481 | H63: 52113 | I63: 69991 | J63: 91927 | K63: 70972 | L63: 51405 | M63: 41642 | N63: 45236 | O63: 47389 | P63: 68218 | Q63: 17319 | R63: 30078 | S63: 4232.2 | T63: 6910.6 | U63: 69358.18 | V63: 74698.58 | W63: 78473.38 | X63: 63858.18 | Y63: 64558.18 | Z63: 87141.18 | AA63: 65569.18 | AB63: 90794.18 | AC63: 254461.18 | AD63: 66434.18
A64: 103.xlsx | B64: Revenue | C64: Other revenues | D64: Total | E64: 122009 | F64: 108729 | G64: 132172 | H64: 116040 | I64: 125538 | J64: 166590 | K64: 89779.5 | L64: 110278 | M64: 96807 | N64: 221066.57 | O64: 121858.75 | P64: 110884.29 | Q64: 156180.45 | R64: 148820 | S64: 148830.5 | T64: 128100 | U64: 135492.18 | V64: 128001.39 | W64: 128482.5 | X64: 141111 | Y64: 173719 | Z64: 213081 | AA64: 123954 | AB64: 173237 | AC64: 165849 | AD64: 272492.25
A65: 103.xlsx | B65: COGS | C65: Total | E65: -2110592.9 | F65: -2145859.3 | G65: -2144427.8 | H65: -2014464.9 | I65: -2139132.5 | J65: -2204651.7 | K65: -2111460.7 | L65: -2098679.3 | M65: -2066296.9 | N65: -1997197.8 | O65: -2229993.9 | P65: -2119617.9 | Q65: -2231857 | R65: -2095494.6 | S65: -1899962.6 | T65: -2232156.9 | U65: -2189785.9 | V65: -2250325.1 | W65: -2133618.1 | X65: -2329291.7 | Y65: -2227789.1 | Z65: -1994367.6 | AA65: -2101179.6 | AB65: -2339857.9 | AC65: -2300092 | AD65: -2168955.7
A66: 103.xlsx | B66: COGS | C66: Medical staff | D66: Total | E66: -1375917.1 | F66: -1410584.6 | G66: -1329656.8 | H66: -1322354.1 | I66: -1334150.8 | J66: -1397043.1 | K66: -1417157.3 | L66: -1414838.6 | M66: -1422407.6 | N66: -1354402.3 | O66: -1479402.9 | P66: -1443023.2 | Q66: -1642654.6 | R66: -1481541.8 | S66: -1318172.2 | T66: -1517472.5 | U66: -1505970.9 | V66: -1535177.3 | W66: -1548090.8 | X66: -1616191.9 | Y66: -1454131.6 | Z66: -1413694.8 | AA66: -1237191.1 | AB66: -1589573.3 | AC66: -1491310.2 | AD66: -1572593.3
A67: 103.xlsx | B67: COGS | C67: Other direct costs | D67: Total | E67: -734675.75 | F67: -735274.68 | G67: -814770.96 | H67: -692110.81 | I67: -804981.66 | J67: -807608.58 | K67: -694303.42 | L67: -683840.68 | M67: -643889.28 | N67: -642795.43 | O67: -750590.98 | P67: -676594.68 | Q67: -589202.4 | R67: -613952.86 | S67: -581790.45 | T67: -714684.4 | U67: -683814.94 | V67: -715147.87 | W67: -585527.3 | X67: -713099.8 | Y67: -773657.47 | Z67: -580672.82 | AA67: -863988.53 | AB67: -750284.6 | AC67: -808781.79 | AD67: -596362.35
A68: 103.xlsx | B68: Gross Profit | C68: Total | E68: 794219.56 | F68: 521234.27 | G68: 521875.63 | H68: 709160.68 | I68: 625163.78 | J68: 646244.83 | K68: 634616.55 | L68: 626249.32 | M68: 640512.83 | N68: 812892.43 | O68: 546790.37 | P68: 721284.96 | Q68: 563095.95 | R68: 809601.73 | S68: 1052609.6 | T68: 755762.1 | U68: 849036.69 | V68: 780701.89 | W68: 1022325.5 | X68: 784172.14 | Y68: 903741.07 | Z68: 1256853.1 | AA68: 1001527.4 | AB68: 824241.53 | AC68: 1125791.8 | AD68: 873705.4
A69: 103.xlsx | B69: OPEX | C69: Total | E69: -150690.09 | F69: -132451.65 | G69: -149136.78 | H69: -140188.67 | I69: -146390 | J69: -165158.33 | K69: -156701.79 | L69: -145211.56 | M69: -145570.45 | N69: -168881.48 | O69: -170991.97 | P69: -182879.63 | Q69: -213987.92 | R69: -185073.93 | S69: -193814.24 | T69: -198902.93 | U69: -190873.68 | V69: -204457.98 | W69: -198295.98 | X69: -180444.57 | Y69: -194726.65 | Z69: -227276.14 | AA69: -247438.01 | AB69: -220707.65 | AC69: -222868.44 | AD69: -212903.71
A70: 103.xlsx | B70: OPEX | C70: Operating expenses | D70: Total | E70: -232596.09 | F70: -192833.65 | G70: -209356.53 | H70: -200053.42 | I70: -202599.74 | J70: -219328.07 | K70: -214928.56 | L70: -209645.31 | M70: -216825.45 | N70: -238780.48 | O70: -228638.77 | P70: -241791.73 | Q70: -270187.92 | R70: -251297.93 | S70: -255037.24 | T70: -257955.93 | U70: -253666.68 | V70: -266640.31 | W70: -260121.87 | X70: -241766.71 | Y70: -256919.65 | Z70: -288495.19 | AA70: -308132.35 | AB70: -281869.04 | AC70: -283737.81 | AD70: -286315.31
A71: 103.xlsx | B71: OPEX | C71: Overhead costs | D71: Total | E71: 81906 | F71: 60382 | G71: 60219.75 | H71: 59864.75 | I71: 56209.74 | J71: 54169.74 | K71: 58226.77 | L71: 64433.75 | M71: 71255 | N71: 69899 | O71: 57646.8 | P71: 58912.1 | Q71: 56200 | R71: 66224 | S71: 61223 | T71: 59053 | U71: 62793 | V71: 62182.33 | W71: 61825.89 | X71: 61322.14 | Y71: 62193 | Z71: 61219.05 | AA71: 60694.34 | AB71: 61161.39 | AC71: 60869.37 | AD71: 73411.6
A72: 103.xlsx | B72: EBITDA1 | C72: Total | E72: 643529.47 | F72: 388782.62 | G72: 372738.85 | H72: 568972.01 | I72: 478773.78 | J72: 481086.5 | K72: 477914.76 | L72: 481037.76 | M72: 494942.38 | N72: 644010.95 | O72: 375798.4 | P72: 538405.33 | Q72: 349108.03 | R72: 624527.8 | S72: 858795.31 | T72: 556859.17 | U72: 658163.01 | V72: 576243.91 | W72: 824029.54 | X72: 603727.57 | Y72: 709014.42 | Z72: 1029576.9 | AA72: 754089.4 | AB72: 603533.88 | AC72: 902923.34 | AD72: 660801.69
A73: 103.xlsx | B73: Management Fee/ Overhead | C73: Total | E73: -226417
A74: 103.xlsx | B74: Management Fee/ Overhead | C74: Management Fee | D74: Total | E74: -78814
A75: 103.xlsx | B75: Management Fee/ Overhead | C75: Service Fee | D75: Total | E75: -147603
A76: 103.xlsx | B76: EBITDA2 | C76: Total | E76: 417112.47 | F76: 388782.62 | G76: 372738.85 | H76: 568972.01 | I76: 478773.78 | J76: 481086.5 | K76: 477914.76 | L76: 481037.76 | M76: 494942.38 | N76: 644010.95 | O76: 375798.4 | P76: 538405.33 | Q76: 349108.03 | R76: 624527.8 | S76: 858795.31 | T76: 556859.17 | U76: 658163.01 | V76: 576243.91 | W76: 824029.54 | X76: 603727.57 | Y76: 709014.42 | Z76: 1029576.9 | AA76: 754089.4 | AB76: 603533.88 | AC76: 902923.34 | AD76: 660801.69
A77: 103.xlsx | B77: Adjustments historical | C77: Total | E77: 0 | F77: 0 | G77: 0 | H77: 0 | I77: 0 | J77: 0 | K77: 0 | L77: 0 | M77: 0 | N77: 0 | O77: 0 | P77: 0 | Q77: 0 | R77: 0 | S77: 0 | T77: 0 | U77: 0 | V77: 0 | W77: 0 | X77: 0 | Y77: 0 | Z77: 0 | AA77: 0 | AB77: 0 | AC77: 0 | AD77: 0
A78: 103.xlsx | B78: EBITDA2 (adjusted) | C78: Total | E78: 417112.47 | F78: 388782.62 | G78: 372738.85 | H78: 568972.01 | I78: 478773.78 | J78: 481086.5 | K78: 477914.76 | L78: 481037.76 | M78: 494942.38 | N78: 644010.95 | O78: 375798.4 | P78: 538405.33 | Q78: 349108.03 | R78: 624527.8 | S78: 858795.31 | T78: 556859.17 | U78: 658163.01 | V78: 576243.91 | W78: 824029.54 | X78: 603727.57 | Y78: 709014.42 | Z78: 1029576.9 | AA78: 754089.4 | AB78: 603533.88 | AC78: 902923.34 | AD78: 660801.69
A79: 103.xlsx | B79: Depreciation & Amortisation | C79: Total | E79: -10403 | F79: -10403 | G79: -10403 | H79: -10403 | I79: -10403 | J79: -10403 | K79: -10403 | L79: -10403 | M79: -10403 | N79: -10403 | O79: -10403 | P79: -10403 | Q79: -10403 | R79: -10403 | T79: -20805 | U79: -10403 | V79: -10403 | W79: -10403 | Y79: -20805 | Z79: -10403 | AA79: -12503 | AB79: -12503 | AC79: -12728 | AD79: -12727
A80: 103.xlsx | B80: Total | C80: Total | E80: 406709.47 | F80: 378379.62 | G80: 362335.85 | H80: 558569.01 | I80: 468370.78 | J80: 470683.5 | K80: 467511.76 | L80: 470634.76 | M80: 484539.38 | N80: 633607.95 | O80: 365395.4 | P80: 528002.33 | Q80: 338705.03 | R80: 614124.8 | S80: 858795.31 | T80: 536054.17 | U80: 647760.01 | V80: 565840.91 | W80: 813626.54 | X80: 603727.57 | Y80: 688209.42 | Z80: 1019173.9 | AA80: 741586.4 | AB80: 591030.88 | AC80: 890195.34 | AD80: 648074.69
A81: 103.xlsx | B81: Total
A82: 103.xlsx
A83: 103.xlsx | B83: Tillämpade filter: CG Item är Selected Period Scenario är inte N/A Value är SEK Inkluderade (4) 2024 (Year), 2025 (Year), 2026 (Year) + January (Month), 2023 (Year) + December (Month) Inkluderade (1) VC VGR (Cost Center Type) + VC StorGöteborg (Business Area) + 103 Grimmered (Name) Scenario är Actual
A84: 104.xlsx | B84: Year Month No | E84: 202312 | F84: 202401 | G84: 202402 | H84: 202403 | I84: 202404 | J84: 202405 | K84: 202406 | L84: 202407 | M84: 202408 | N84: 202409 | O84: 202410 | P84: 202411 | Q84: 202412 | R84: 202501 | S84: 202502 | T84: 202503 | U84: 202504 | V84: 202505 | W84: 202506 | X84: 202507 | Y84: 202508 | Z84: 202509 | AA84: 202510 | AB84: 202511 | AC84: 202512 | AD84: 202601
A85: 104.xlsx | B85: Scenario | E85: Actual | F85: Actual | G85: Actual | H85: Actual | I85: Actual | J85: Actual | K85: Actual | L85: Actual | M85: Actual | N85: Actual | O85: Actual | P85: Actual | Q85: Actual | R85: Actual | S85: Actual | T85: Actual | U85: Actual | V85: Actual | W85: Actual | X85: Actual | Y85: Actual | Z85: Actual | AA85: Actual | AB85: Actual | AC85: Actual | AD85: Actual
A86: 104.xlsx | B86: ElementName | C86: Reference Account | D86: Cluster | E86: Profit and Loss Table | F86: Profit and Loss Table | G86: Profit and Loss Table | H86: Profit and Loss Table | I86: Profit and Loss Table | J86: Profit and Loss Table | K86: Profit and Loss Table | L86: Profit and Loss Table | M86: Profit and Loss Table | N86: Profit and Loss Table | O86: Profit and Loss Table | P86: Profit and Loss Table | Q86: Profit and Loss Table | R86: Profit and Loss Table | S86: Profit and Loss Table | T86: Profit and Loss Table | U86: Profit and Loss Table | V86: Profit and Loss Table | W86: Profit and Loss Table | X86: Profit and Loss Table | Y86: Profit and Loss Table | Z86: Profit and Loss Table | AA86: Profit and Loss Table | AB86: Profit and Loss Table | AC86: Profit and Loss Table | AD86: Profit and Loss Table
A87: 104.xlsx | B87: Revenue | C87: Total | E87: 2509329.4 | F87: 2428050 | G87: 2442971.3 | H87: 2487015.4 | I87: 2517287.1 | J87: 2590609.8 | K87: 2483819.5 | L87: 2406327.2 | M87: 2509874.7 | N87: 2581995 | O87: 2607268.5 | P87: 2681384.6 | Q87: 2557917.4 | R87: 2690098 | S87: 2633121.8 | T87: 2704302.1 | U87: 2613503.2 | V87: 2616857.9 | W87: 2779912.1 | X87: 2618728.9 | Y87: 2510375.6 | Z87: 2724550 | AA87: 2745547.5 | AB87: 2755020.6 | AC87: 2843766.1 | AD87: 2760524.7
A88: 104.xlsx | B88: Revenue | C88: Revenues | D88: Total | E88: 2389170.4 | F88: 2310550 | G88: 2300667.3 | H88: 2350487.9 | I88: 2382283.6 | J88: 2344744.8 | K88: 2350345 | L88: 2314369.2 | M88: 2362473.7 | N88: 2352540.3 | O88: 2382142.5 | P88: 2457934.1 | Q88: 2351559.4 | R88: 2471080 | S88: 2470404.8 | T88: 2515974.6 | U88: 2484829.5 | V88: 2485687.9 | W88: 2580232.1 | X88: 2529480.9 | Y88: 2469886.5 | Z88: 2558073.5 | AA88: 2599150.5 | AB88: 2543353.1 | AC88: 2639565.3 | AD88: 2566319.2
A89: 104.xlsx | B89: Revenue | C89: Revenues | D89: RG Huvudintäkter | E89: 2325319 | F89: 2282442.6 | G89: 2278606.3 | H89: 2326465.4 | I89: 2320123.4 | J89: 2310671.8 | K89: 2346140.1 | L89: 2292339.2 | M89: 2337895.7 | N89: 2329807.3 | O89: 2356163.9 | P89: 2428389.1 | Q89: 2340487.3 | R89: 2456969.1 | S89: 2456678.2 | T89: 2469968 | U89: 2480600.7 | V89: 2480600.7 | W89: 2562652.9 | X89: 2524475.5 | Y89: 2467942.5 | Z89: 2480744 | AA89: 2557696.4 | AB89: 2537571.6 | AC89: 2552913.3 | AD89: 2513531.2
A90: 104.xlsx | B90: Revenue | C90: Revenues | D90: Patientintäkter | E90: 64501.43 | F90: 15773.36 | G90: 8350 | H90: 5414.43 | I90: 53992.2 | J90: 5390 | K90: -0.12 | L90: 19145 | M90: 16280 | N90: 15200 | O90: 14578.61 | P90: 0 | Q90: 6516.11 | R90: 4865.31 | S90: 5849.79 | T90: 39035.89 | W90: 14863.98 | Z90: 45394.46 | AA90: 36582.14 | AB90: 880.53
A91: 104.xlsx | B91: Revenue | C91: Revenues | D91: Övriga intäkter | E91: -650 | F91: 12334 | G91: 13711 | H91: 18608 | I91: 8168 | J91: 28683 | K91: 4205 | L91: 2885 | M91: 8298 | N91: 7533 | O91: 11400 | P91: 29545 | Q91: 4556 | R91: 9245.6 | S91: 7876.8 | T91: 6970.8 | U91: 4228.8 | V91: 5087.2 | W91: 2715.2 | X91: 5005.4 | Y91: 1944 | Z91: 31935 | AA91: 4872 | AB91: 4901 | AC91: 86652 | AD91: 52788
A92: 104.xlsx | B92: Revenue | C92: Other revenues | D92: Total | E92: 120159 | F92: 117500 | G92: 142304 | H92: 136527.5 | I92: 135003.5 | J92: 245865 | K92: 133474.5 | L92: 91958 | M92: 147401 | N92: 229454.76 | O92: 225126 | P92: 223450.5 | Q92: 206358 | R92: 219018 | S92: 162717 | T92: 188327.5 | U92: 128673.66 | V92: 131170 | W92: 199680 | X92: 89248 | Y92: 40489.01 | Z92: 166476.5 | AA92: 146397 | AB92: 211667.5 | AC92: 204200.83 | AD92: 194205.42
A93: 104.xlsx | B93: COGS | C93: Total | E93: -1928158.7 | F93: -1879854.3 | G93: -1815907.9 | H93: -1880134.1 | I93: -1931309.1 | J93: -1996617.2 | K93: -1941100.5 | L93: -1944268.4 | M93: -2027362.1 | N93: -1951792.6 | O93: -2170162.8 | P93: -2083598.1 | Q93: -1936260.9 | R93: -1905764.2 | S93: -1805833.8 | T93: -1790095.4 | U93: -1866283.6 | V93: -1857217.9 | W93: -1935722.5 | X93: -1803460.6 | Y93: -1876079.7 | Z93: -1751690 | AA93: -1902350.4 | AB93: -2023748.8 | AC93: -1979124.5 | AD93: -2095923.8
A94: 104.xlsx | B94: COGS | C94: Medical staff | D94: Total | E94: -1280079 | F94: -1202898.6 | G94: -1213219.9 | H94: -1261114.4 | I94: -1327154.5 | J94: -1337064.5 | K94: -1396818.2 | L94: -1413507.8 | M94: -1402524.4 | N94: -1363993 | O94: -1466002.5 | P94: -1374774.8 | Q94: -1425820 | R94: -1398695.6 | S94: -1251826.6 | T94: -1244887.1 | U94: -1304324.9 | V94: -1311728.1 | W94: -1325681.4 | X94: -1321167 | Y94: -1276929 | Z94: -1225370.7 | AA94: -1264317.8 | AB94: -1454821.2 | AC94: -1366290.6 | AD94: -1551672.6
A95: 104.xlsx | B95: COGS | C95: Other direct costs | D95: Total | E95: -648079.65 | F95: -676955.66 | G95: -602687.97 | H95: -619019.73 | I95: -604154.53 | J95: -659552.72 | K95: -544282.32 | L95: -530760.63 | M95: -624837.68 | N95: -587799.56 | O95: -704160.36 | P95: -708823.31 | Q95: -510440.9 | R95: -507068.58 | S95: -554007.2 | T95: -545208.23 | U95: -561958.65 | V95: -545489.84 | W95: -610041.11 | X95: -482293.64 | Y95: -599150.72 | Z95: -526319.33 | AA95: -638032.52 | AB95: -568927.57 | AC95: -612833.85 | AD95: -544251.2
A96: 104.xlsx | B96: Gross Profit | C96: Total | E96: 581170.71 | F96: 548195.71 | G96: 627063.42 | H96: 606881.29 | I96: 585978.02 | J96: 593992.54 | K96: 542719.03 | L96: 462058.78 | M96: 482512.54 | N96: 630202.47 | O96: 437105.63 | P96: 597786.46 | Q96: 621656.46 | R96: 784333.88 | S96: 827287.96 | T96: 914206.79 | U96: 747219.57 | V96: 759639.97 | W96: 844189.6 | X96: 815268.26 | Y96: 634295.86 | Z96: 972859.98 | AA96: 843197.19 | AB96: 731271.87 | AC96: 864641.68 | AD96: 664600.89
A97: 104.xlsx | B97: OPEX | C97: Total | E97: -107009.57 | F97: -199286.76 | G97: -192813.21 | H97: -201269.65 | I97: -209258.95 | J97: -198384.04 | K97: -219485.32 | L97: -190120.07 | M97: -194821.16 | N97: -202952.56 | O97: -205092.61 | P97: -206098.19 | Q97: -213063.7 | R97: -203136.35 | S97: -219000.94 | T97: -222518.64 | U97: -223189.27 | V97: -231286.36 | W97: -223024.89 | X97: -211117.76 | Y97: -223493.27 | Z97: -268035.07 | AA97: -230644.74 | AB97: -232881.95 | AC97: -264759.15 | AD97: -249889.73
A98: 104.xlsx | B98: OPEX | C98: Operating expenses | D98: Total | E98: -114114.57 | F98: -208286.76 | G98: -201813.21 | H98: -210269.65 | I98: -211086.95 | J98: -207384.04 | K98: -228485.32 | L98: -199120.07 | M98: -203821.16 | N98: -210967.35 | O98: -213106.55 | P98: -214112.13 | Q98: -221077.64 | R98: -211350.29 | S98: -227412.09 | T98: -230535.37 | U98: -231403.21 | V98: -239500.3 | W98: -231238.83 | X98: -219331.7 | Y98: -231707.21 | Z98: -276249.01 | AA98: -238858.68 | AB98: -241095.89 | AC98: -272973.09 | AD98: -257897.25
A99: 104.xlsx | B99: OPEX | C99: Overhead costs | D99: Total | E99: 7105 | F99: 9000 | G99: 9000 | H99: 9000 | I99: 1828 | J99: 9000 | K99: 9000 | L99: 9000 | M99: 9000 | N99: 8014.79 | O99: 8013.94 | P99: 8013.94 | Q99: 8013.94 | R99: 8213.94 | S99: 8411.15 | T99: 8016.73 | U99: 8213.94 | V99: 8213.94 | W99: 8213.94 | X99: 8213.94 | Y99: 8213.94 | Z99: 8213.94 | AA99: 8213.94 | AB99: 8213.94 | AC99: 8213.94 | AD99: 8007.52
A100: 104.xlsx | B100: EBITDA1 | C100: Total | E100: 474161.14 | F100: 348908.95 | G100: 434250.21 | H100: 405611.64 | I100: 376719.07 | J100: 395608.5 | K100: 323233.71 | L100: 271938.71 | M100: 287691.38 | N100: 427249.91 | O100: 232013.02 | P100: 391688.27 | Q100: 408592.76 | R100: 581197.53 | S100: 608287.02 | T100: 691688.15 | U100: 524030.3 | V100: 528353.61 | W100: 621164.71 | X100: 604150.5 | Y100: 410802.59 | Z100: 704824.91 | AA100: 612552.45 | AB100: 498389.92 | AC100: 599882.53 | AD100: 414711.16
...

Sheet Info
B4: Antal listade pat | C4: 202312 | D4: 202401 | E4: 202402 | F4: 202403 | G4: 202404 | H4: 202405 | I4: 202406 | J4: 202407 | K4: 202408 | L4: 202409 | M4: 202410 | N4: 202411 | O4: 202412 | P4: 202501 | Q4: 202502 | R4: 202503 | S4: 202504 | T4: 202505 | U4: 202506 | V4: 202507 | W4: 202508 | X4: 202509 | Y4: 202510 | Z4: 202511 | AA4: 202512 | AB4: 202601 | AC4: 202602 | AD4: KST | AE4: Diff
B5: Citysjukhuset Plus 7 vårdcentral | C5: 5094 | D5: 5121 | E5: 5169 | F5: 5181 | G5: 5163 | H5: 5188 | I5: 5209 | J5: 5191 | K5: 5206 | L5: 5220 | M5: 5284 | N5: 5400 | O5: 5493 | P5: 6477 | Q5: 6493 | R5: 6484 | S5: 6465 | T5: 6467 | U5: 6437 | V5: 6417 | W5: 6399 | X5: 6404 | Y5: 6376 | Z5: 6338 | AA5: 6299 | AB5: 6276 | AC5: 6258 | AD5: 4020 | AE5: =AC5-AB5 -> -18
B6: Kvarterskliniken Avenyn | C6: 5557 | D6: 5568 | E6: 5578 | F6: 5589 | G6: 5608 | H6: 5603 | I6: 5580 | J6: 5601 | K6: 5627 | L6: 5653 | M6: 5691 | N6: 5786 | O6: 5872 | P6: 6055 | Q6: 6038 | R6: 6037 | S6: 6036 | T6: 6015 | U6: 6004 | V6: 6018 | W6: 6001 | X6: 5975 | Y6: 5990 | Z6: 5984 | AA6: 5971 | AB6: 5981 | AC6: 5963 | AD6: 302 | AE6: =AC6-AB6 -> -18
B7: Kvarterskliniken Husaren | C7: 4304 | D7: 4262 | E7: 4221 | F7: 4188 | G7: 4176 | H7: 4152 | I7: 4144 | J7: 4155 | K7: 4149 | L7: 4170 | M7: 4145 | N7: 4147 | O7: 4146 | P7: 4422 | Q7: 4403 | R7: 4388 | S7: 4379 | T7: 4379 | U7: 4352 | V7: 4329 | W7: 4320 | X7: 4293 | Y7: 4287 | Z7: 4273 | AA7: 4266 | AB7: 4251 | AC7: 4226 | AD7: 304 | AE7: =AC7-AB7 -> -25
B8: Kvarterskliniken Karlastaden | C8: 0 | D8: 0 | E8: 0 | F8: 0 | G8: 0 | H8: 0 | I8: 0 | J8: 0 | K8: 0 | L8: 195 | M8: 358 | N8: 469 | O8: 546 | P8: 635 | Q8: 705 | R8: 767 | S8: 826 | T8: 878 | U8: 954 | V8: 1025 | W8: 1153 | X8: 1275 | Y8: 1376 | Z8: 1456 | AA8: 1521 | AB8: 1613 | AC8: 1679 | AD8: 15 | AE8: =AC8-AB8 -> 66
B9: Kvarterskliniken Lorensberg | C9: 1621 | D9: 1615 | E9: 1609 | F9: 1604 | G9: 1599 | H9: 1591 | I9: 1577 | J9: 1568 | K9: 1548 | L9: 1546 | M9: 1556 | N9: 1566 | O9: 1570 | P9: 1627 | Q9: 1617 | R9: 1623 | S9: 1609 | T9: 1602 | U9: 1588 | V9: 1573 | W9: 1561 | X9: 1547 | Y9: 1539 | Z9: 1531 | AA9: 1524 | AB9: 1506 | AC9: 1501 | AD9: 303 | AE9: =AC9-AB9 -> -5
B10: Omtanken Vårdcentral Frölunda Torg | C10: 8160 | D10: 8140 | E10: 8115 | F10: 8102 | G10: 8110 | H10: 8098 | I10: 8097 | J10: 8077 | K10: 8085 | L10: 8125 | M10: 8128 | N10: 8130 | O10: 8148 | P10: 8168 | Q10: 8167 | R10: 8191 | S10: 8187 | T10: 8155 | U10: 8133 | V10: 8129 | W10: 8149 | X10: 8158 | Y10: 8143 | Z10: 8124 | AA10: 8088 | AB10: 8033 | AC10: 8009 | AD10: 102 | AE10: =AC10-AB10 -> -24
B11: Omtanken Vårdcentral Grimmered | C11: 6273 | D11: 6299 | E11: 6278 | F11: 6310 | G11: 6311 | H11: 6327 | I11: 6321 | J11: 6371 | K11: 6451 | L11: 6525 | M11: 6612 | N11: 6650 | O11: 6670 | P11: 6731 | Q11: 6754 | R11: 6820 | S11: 6816 | T11: 6869 | U11: 6890 | V11: 6878 | W11: 6918 | X11: 6940 | Y11: 6966 | Z11: 6951 | AA11: 6977 | AB11: 6971 | AC11: 6969 | AD11: 103 | AE11: =AC11-AB11 -> -2
B12: Omtanken Vårdcentral Kviberg | C12: 3982 | D12: 4021 | E12: 4081 | F12: 4136 | G12: 4144 | H12: 4146 | I12: 4073 | J12: 4038 | K12: 4065 | L12: 4093 | M12: 4105 | N12: 4094 | O12: 4106 | P12: 4161 | Q12: 4169 | R12: 4194 | S12: 4180 | T12: 4219 | U12: 4224 | V12: 4223 | W12: 4253 | X12: 4265 | Y12: 4270 | Z12: 4280 | AA12: 4285 | AB12: 4325 | AC12: 4332 | AD12: 110 | AE12: =AC12-AB12 -> 7
B13: Omtanken Vårdcentral Kållered | C13: 1568 | D13: 1565 | E13: 1561 | F13: 1558 | G13: 1552 | H13: 1552 | I13: 1573 | J13: 1584 | K13: 1570 | L13: 1577 | M13: 1578 | N13: 1564 | O13: 1553 | P13: 1556 | Q13: 1558 | R13: 1567 | S13: 1553 | T13: 1541 | U13: 1541 | V13: 1539 | W13: 1539 | X13: 1527 | Y13: 1519 | Z13: 1511 | AA13: 1528 | AB13: 1541 | AC13: 1535 | AD13: 109 | AE13: =AC13-AB13 -> -6
B14: Omtanken Vårdcentral Landala | C14: 6618 | D14: 6636 | E14: 6673 | F14: 6670 | G14: 6649 | H14: 6656 | I14: 6652 | J14: 6631 | K14: 6675 | L14: 6695 | M14: 6725 | N14: 6758 | O14: 6751 | P14: 6992 | Q14: 6983 | R14: 6967 | S14: 6959 | T14: 6866 | U14: 6774 | V14: 6712 | W14: 6696 | X14: 6634 | Y14: 6564 | Z14: 6537 | AA14: 6481 | AB14: 6448 | AC14: 6431 | AD14: 106 | AE14: =AC14-AB14 -> -17
B15: Omtanken Vårdcentral Majorna | C15: 6259 | D15: 6254 | E15: 6241 | F15: 6271 | G15: 6277 | H15: 6292 | I15: 6303 | J15: 6305 | K15: 6353 | L15: 6406 | M15: 6421 | N15: 6425 | O15: 6444 | P15: 6525 | Q15: 6515 | R15: 6537 | S15: 6546 | T15: 6536 | U15: 6520 | V15: 6512 | W15: 6508 | X15: 6490 | Y15: 6477 | Z15: 6446 | AA15: 6420 | AB15: 6381 | AC15: 6372 | AD15: 104 | AE15: =AC15-AB15 -> -9
B16: Omtanken Vårdcentral Olskroken | C16: 3444 | D16: 3486 | E16: 3544 | F16: 3620 | G16: 3666 | H16: 3727 | I16: 3769 | J16: 3827 | K16: 3912 | L16: 4013 | M16: 4114 | N16: 4170 | O16: 4217 | P16: 4374 | Q16: 4451 | R16: 4498 | S16: 4487 | T16: 4503 | U16: 4528 | V16: 4546 | W16: 4619 | X16: 4679 | Y16: 4707 | Z16: 4740 | AA16: 4776 | AB16: 4809 | AC16: 4845 | AD16: 111 | AE16: =AC16-AB16 -> 36
... B18: Omtanken Vårdcentral Åby | C18: 5092 | D18: 5091 | E18: 5085 | F18: 5063 | G18: 5057 | H18: 5057 | I18: 5054 | J18: 5059 | K18: 5045 | L18: 5032 | M18: 5035 | N18: 5061 | O18: 5063 | P18: 5052 | Q18: 5075 | R18: 5063 | S18: 5030 | T18: 5041 | U18: 5030 | V18: 5020 | W18: 5022 | X18: 5013 | Y18: 5009 | Z18: 5019 | AA18: 5028 | AB18: 5043 | AC18: 5034 | AD18: 108 | AE18: =AC18-AB18 -> -9
C19: =SUM(C5:C18) -> 63760 | D19: =SUM(D5:D18) -> 63838 | E19: =SUM(E5:E18) -> 63938 | F19: =SUM(F5:F18) -> 64083 | G19: =SUM(G5:G18) -> 64141 | H19: =SUM(H5:H18) -> 64235 | I19: =SUM(I5:I18) -> 64209 | J19: =SUM(J5:J18) -> 64278 | ... AC19: =SUM(AC5:AC18) -> 68777 | AE19: =AC19-AB19 -> -22
D20: =D19-C19 -> 78 | E20: =E19-D19 -> 100 | F20: =F19-E19 -> 145 | G20: =G19-F19 -> 58 | H20: =H19-G19 -> 94 | I20: =I19-H19 -> -26 | J20: =J19-I19 -> 69 | K20: =K19-J19 -> 284 | ... AC20: =AC19-AB19 -> -22
B21: Antal listningpoäng | C21: 202312 | D21: 202401 | E21: 202402 | F21: 202403 | G21: 202404 | H21: 202405 | I21: 202406 | J21: 202407 | K21: 202408 | L21: 202409 | M21: 202410 | N21: 202411 | O21: 202412 | P21: 202501 | Q21: 202502 | R21: 202503 | S21: 202504 | T21: 202505 | U21: 202506 | V21: 202507 | W21: 202508 | X21: 202509 | Y21: 202510 | Z21: 202511 | AA21: 202512 | AB21: 202601 | AC21: 202602
B22: Citysjukhuset Plus 7 vårdcentral | C22: 1418.148 | D22: 1427.5046 | E22: 1440.5564 | F22: 1453.886 | G22: 1455.1349 | H22: 1463.8688 | I22: 1469.7928 | J22: 1463.9962 | K22: 1474.3264 | L22: 1480.9587 | M22: 1503.829 | N22: 1549.6673 | O22: 1576.4664 | P22: 1819.6745 | Q22: 1818.7075 | R22: 1819.192 | S22: 1811.63 | T22: 1821 | U22: 1809.81 | V22: 1806.84 | W22: 1805.32 | X22: 1804 | Y22: 1792.6021 | Z22: 1785.502 | AA22: 1775.23 | AB22: 1772.6348 | AC22: 1777.8733 | AD22: 4020
B23: Kvarterskliniken Avenyn | C23: 1904.024 | D23: 1903.5358 | E23: 1905.3599 | F23: 1910.7074 | G23: 1916.1973 | H23: 1917.5221 | I23: 1905.9663 | J23: 1908.5777 | K23: 1912.7467 | L23: 1913.7144 | M23: 1935.6688 | N23: 1979.79 | O23: 2017.7743 | P23: 2065.2218 | Q23: 2063.1477 | R23: 2055.7361 | S23: 2062.2038 | T23: 2054 | U23: 2054 | V23: 2067 | W23: 2071.88 | X23: 2057 | Y23: 2059.4543 | Z23: 2057.2127 | AA23: 2055.999 | AB23: 2062.6849 | AC23: 2054.543 | AD23: 302
B24: Kvarterskliniken Husaren | C24: 1295.7489 | D24: 1284.3455 | E24: 1278.0028 | F24: 1270.0322 | G24: 1268.4389 | H24: 1264.1947 | I24: 1259.4946 | J24: 1260.0752 | K24: 1259.9805 | L24: 1256.0942 | M24: 1260.986 | N24: 1249.8487 | O24: 1245.2986 | P24: 1322.6351 | Q24: 1314.5113 | R24: 1313.2617 | S24: 1312.5025 | T24: 1303 | U24: 1303.95 | V24: 1302.35 | W24: 1296.61 | X24: 1288 | Y24: 1276.1561 | Z24: 1276.9972 | AA24: 1277.136 | AB24: 1286.7833 | AC24: 1279.5822 | AD24: 304
B25: Kvarterskliniken Karlastaden | C25: 0 | D25: 0 | E25: 0 | F25: 0 | G25: 0 | H25: 0 | I25: 0 | J25: 0 | K25: 0 | L25: 48.700658 | M25: 96.244616 | N25: 118.65989 | O25: 144.6085 | P25: 169.49809 | Q25: 187.13266 | R25: 207.46878 | S25: 228.67908 | T25: 240 | U25: 263 | V25: 275.84 | W25: 297.61 | X25: 324 | Y25: 348.86238 | Z25: 369.47882 | AA25: 383.641 | AB25: 412.51453 | AC25: 429.35025 | AD25: 15
B26: Kvarterskliniken Lorensberg | C26: 523.81771 | D26: 523.64099 | E26: 524.9131 | F26: 522.29086 | G26: 521.70818 | H26: 522.54421 | I26: 523.50769 | J26: 523.33477 | K26: 518.708 | L26: 520.73776 | M26: 526.60806 | N26: 524.85967 | O26: 526.5664 | P26: 541.18391 | Q26: 538.09678 | R26: 537.57928 | S26: 531.65464 | T26: 532 | U26: 530 | V26: 526 | W26: 529.81 | X26: 528 | Y26: 524.5909 | Z26: 523.32393 | AA26: 522.702 | AB26: 520.10755 | AC26: 518.84278 | AD26: 303
B27: Omtanken Vårdcentral Frölunda Torg | C27: 2666.6628 | D27: 2664.4166 | E27: 2675.5121 | F27: 2670.09 | G27: 2671.9079 | H27: 2656.6497 | I27: 2664.03 | J27: 2659.9214 | K27: 2646.737 | L27: 2661.1881 | M27: 2663.0191 | N27: 2659.3426 | O27: 2674.9092 | P27: 2672.3042 | Q27: 2669.5688 | R27: 2674.2258 | S27: 2676.924 | T27: 2679 | U27: 2667 | V27: 2668.32 | W27: 2678.35 | X27: 2674 | Y27: 2661.4013 | Z27: 2651.7317 | AA27: 2642.123 | AB27: 2621.6264 | AC27: 2604.1029 | AD27: 102
B28: Omtanken Vårdcentral Grimmered | C28: 2014.7678 | D28: 2031.0918 | E28: 2027.6241 | F28: 2028.0519 | G28: 2015.6309 | H28: 2035.5099 | I28: 2047.0257 | J28: 2055.4542 | K28: 2070.4378 | L28: 2081.2006 | M28: 2117.0262 | N28: 2126.3342 | O28: 2131.3652 | P28: 2147.0344 | Q28: 2145.0899 | R28: 2170.8674 | S28: 2168.6043 | T28: 2183 | U28: 2213 | V28: 2201.69 | W28: 2197 | X28: 2193 | Y28: 2210.1801 | Z28: 2210.93 | AA28: 2230.888 | AB28: 2242.4798 | AC28: 2246.9921 | AD28: 103
B29: Omtanken Vårdcentral Kviberg | C29: 1216.0798 | D29: 1238.4741 | E29: 1270.2314 | F29: 1309.579 | G29: 1323.5485 | H29: 1340.2792 | I29: 1239.1595 | J29: 1170.9282 | K29: 1156.9968 | L29: 1173.663 | M29: 1172.8969 | N29: 1155.3642 | O29: 1156.4775 | P29: 1174.5014 | Q29: 1174.608 | R29: 1181.0767 | S29: 1164.85 | T29: 1193 | U29: 1208 | V29: 1202.81 | W29: 1200 | X29: 1193 | Y29: 1197.9489 | Z29: 1212.2265 | AA29: 1218.456 | AB29: 1244.5998 | AC29: 1257.1429 | AD29: 110
B30: Omtanken Vårdcentral Kållered | C30: 453.248 | D30: 449.42548 | E30: 442.21365 | F30: 447.9617 | G30: 442.08169 | H30: 443.4498 | I30: 443.95001 | J30: 449.03375 | K30: 443.24275 | L30: 446.14863 | M30: 440.85267 | N30: 437.70511 | O30: 437.81015 | P30: 434.00445 | Q30: 433.53083 | R30: 438.15103 | S30: 436.7541 | T30: 430 | U30: 433 | V30: 430.43 | W30: 431.76 | X30: 429 | Y30: 427.03265 | Z30: 420.61049 | AA30: 425.142 | AB30: 427.61583 | AC30: 422.71977 | AD30: 109
B31: Omtanken Vårdcentral Landala | C31: 1773.2739 | D31: 1776.9541 | E31: 1789.3903 | F31: 1786.3537 | G31: 1774.7599 | H31: 1780.4125 | I31: 1783.4177 | J31: 1781.4637 | K31: 1792.9008 | L31: 1813.1635 | M31: 1834.1222 | N31: 1871.1094 | O31: 1881.1119 | P31: 1954.7461 | Q31: 1947.7604 | R31: 1946.4839 | S31: 1949.629 | T31: 1917 | U31: 1896 | V31: 1879.57 | W31: 1872.3 | X31: 1856 | Y31: 1840.815 | Z31: 1838.9235 | AA31: 1833.813 | AB31: 1833.3992 | AC31: 1828.9247 | AD31: 106
B32: Omtanken Vårdcentral Majorna | C32: 1891.2464 | D32: 1892.653 | E32: 1910.0853 | F32: 1923.5407 | G32: 1940.3587 | H32: 1950.2907 | I32: 1953.2692 | J32: 1954.5968 | K32: 1978.2504 | L32: 1995.726 | M32: 2012.66 | N32: 2009.3677 | O32: 2014.7344 | P32: 2018.5867 | Q32: 2019.8604 | R32: 2042.2714 | S32: 2045.5672 | T32: 2033 | U32: 2037 | V32: 2031.37 | W32: 2022.83 | X32: 2020 | Y32: 2020.4947 | Z32: 2000.3658 | AA32: 1994.534 | AB32: 1987.2639 | AC32: 1967.0332 | AD32: 104
B33: Omtanken Vårdcentral Olskroken | C33: 1126.1003 | D33: 1144.7968 | E33: 1187.04 | F33: 1213.9066 | G33: 1239.8548 | H33: 1280.8001 | I33: 1305.6438 | J33: 1341.109 | K33: 1358.1993 | L33: 1376.8282 | M33: 1409.3586 | N33: 1443.6362 | O33: 1458.0202 | P33: 1513.4803 | Q33: 1544.0182 | R33: 1578.9385 | S33: 1575.1461 | T33: 1569 | U33: 1595 | V33: 1604.17 | W33: 1624 | X33: 1652 | Y33: 1653.5613 | Z33: 1674.5155 | AA33: 1684.434 | AB33: 1696.9696 | AC33: 1721.5702 | AD33: 111
... B35: Omtanken Vårdcentral Åby | C35: 1592.926 | D35: 1585.0119 | E35: 1595.499 | F35: 1598.5341 | G35: 1613.4864 | H35: 1605.0992 | I35: 1606.2454 | J35: 1617.8121 | K35: 1616.1174 | L35: 1616.337 | M35: 1609.6472 | N35: 1630.4355 | O35: 1622.9446 | P35: 1615.8311 | Q35: 1617.4825 | R35: 1612.9131 | S35: 1603.1143 | T35: 1603 | U35: 1596 | V35: 1586.95 | W35: 1581.42 | X35: 1579 | Y35: 1573.8367 | Z35: 1580.5985 | AA35: 1578.722 | AB35: 1584.594 | AC35: 1587.5775 | AD35: 108
C36: =SUM(C22:C35) -> 19501.258 | D36: =SUM(D22:D35) -> 19548.719 | E36: =SUM(E22:E35) -> 19690.007 | F36: =SUM(F22:F35) -> 19786.079 | G36: =SUM(G22:G35) -> 19847.919 | H36: =SUM(H22:H35) -> 19933.757 | I36: =SUM(I22:I35) -> 19883.608 | J36: =SUM(J22:J35) -> 19871.158 | ... AC36: =SUM(AC22:AC35) -> 21330.334
D37: =D36-C36 -> 47.460234 | E37: =E36-D36 -> 141.28831 | F37: =F36-E36 -> 96.071714 | G37: =G36-F36 -> 61.840846 | H37: =H36-G36 -> 85.837768 | I37: =I36-H36 -> -50.149212 | J37: =J36-I36 -> -12.450405 | K37: =K36-J36 -> 53.111306 | ... AA37: =AA36-Z36 -> 16.989087
B38: ACG casemix | C38: 202312 | D38: 202401 | E38: 202402 | F38: 202403 | G38: 202404 | H38: 202405 | I38: 202406 | J38: 202407 | K38: 202408 | L38: 202409 | M38: 202410 | N38: 202411 | O38: 202412 | P38: 202501 | Q38: 202502 | R38: 202503 | S38: 202504 | T38: 202505 | U38: 202506 | V38: 202507 | W38: 202508 | X38: 202509 | Y38: 202510 | Z38: 202511 | AA38: 202512 | AB38: 202601 | AC38: 202602
B39: Citysjukhuset Plus 7 vårdcentral | C39: 1.0614071 | D39: 0.97451976 | E39: 0.98125772 | F39: 0.98832216 | G39: 0.99099207 | H39: 0.9992378 | I39: 1.007592 | J39: 1.0228048 | K39: 1.0226357 | L39: 1.0334026 | M39: 1.0417446 | N39: 1.0530516 | O39: 1.0716561 | P39: 1.0004408 | Q39: 0.91926722 | R39: 0.93233529 | S39: 0.94249874 | T39: 0.95107248 | U39: 0.95190702 | V39: 0.96322927 | W39: 0.96961355 | X39: 0.98133215 | Y39: 0.99035259 | Z39: 0.99304919 | AA39: 1.0143835 | AB39: 1.0067129 | AC39: 1.0059425 | AD39: 4020
B40: Kvarterskliniken Avenyn | C40: 1.075854 | D40: 1.0382789 | E40: 1.0379765 | F40: 1.0339203 | G40: 1.0373011 | H40: 1.0422695 | I40: 1.0397034 | J40: 1.0388481 | K40: 1.0280763 | L40: 1.0251968 | M40: 1.0338745 | N40: 1.0365646 | O40: 1.0401888 | P40: 1.0275679 | Q40: 0.99454842 | R40: 0.99969372 | S40: 0.99595987 | T40: 0.99771068 | U40: 0.98556347 | V40: 0.98021903 | W40: 0.97543844 | X40: 0.98015176 | Y40: 0.98970981 | Z40: 0.98740021 | AA40: 1.002564 | AB40: 0.99909259 | AC40: 1.0086668 | AD40: 302
B41: Kvarterskliniken Husaren | C41: 1.0128972 | D41: 0.98877368 | E41: 0.99337215 | F41: 0.99566803 | G41: 0.98475143 | H41: 0.98425641 | I41: 0.96612632 | J41: 0.95385616 | K41: 0.93480236 | L41: 0.92254799 | M41: 0.91027484 | N41: 0.90466167 | O41: 0.89559576 | P41: 0.87927581 | Q41: 0.85566579 | R41: 0.86615536 | S41: 0.86974206 | T41: 0.8817445 | U41: 0.88279128 | V41: 0.89443921 | W41: 0.90232456 | X41: 0.90421144 | Y41: 0.91182601 | Z41: 0.91242282 | AA41: 0.93226291 | AB41: 0.935644 | AC41: 0.94237833 | AD41: 304
B42: Kvarterskliniken Karlastaden | C42: 0 | D42: 0 | E42: 0 | F42: 0 | G42: 0 | H42: 0 | I42: 0 | J42: 0 | K42: 0 | L42: 0.63217057 | M42: 0.64730782 | N42: 0.74855712 | O42: 0.8127165 | P42: 0.84829632 | Q42: 0.84788537 | R42: 0.86382487 | S42: 0.87180089 | T42: 0.91030146 | U42: 0.92467725 | V42: 0.9403678 | W42: 0.91189916 | X42: 0.90291571 | Y42: 0.92886065 | Z42: 0.95469265 | AA42: 0.97126983 | AB42: 0.98795358 | AC42: 1.0042477 | AD42: 15
B43: Kvarterskliniken Lorensberg | C43: 0.90236362 | D43: 0.86693574 | E43: 0.87198303 | F43: 0.88203489 | G43: 0.88721764 | H43: 0.89133838 | I43: 0.90970316 | J43: 0.92034375 | K43: 0.91036353 | L43: 0.90250965 | M43: 0.91269318 | N43: 0.89347751 | O43: 0.89242936 | P43: 0.87113736 | Q43: 0.84556546 | R43: 0.84319421 | S43: 0.85260109 | T43: 0.85365011 | U43: 0.85490046 | V43: 0.85275455 | W43: 0.84483907 | X43: 0.84488721 | Y43: 0.83872827 | Z43: 0.83728296 | AA43: 0.83749337 | AB43: 0.84340985 | AC43: 0.85321029 | AD43: 303
B44: Omtanken Vårdcentral Frölunda Torg | C44: 0.99226622 | D44: 0.9941307 | E44: 0.99623528 | F44: 1.0030491 | G44: 1.0080654 | H44: 1.0132702 | I44: 1.0174282 | J44: 1.0211185 | K44: 1.0170662 | L44: 1.0256269 | M44: 1.0241464 | N44: 1.0269294 | O44: 1.0383104 | P44: 1.0379828 | Q44: 1.0431162 | R44: 1.0429832 | S44: 1.0404559 | T44: 1.0298318 | U44: 1.0247453 | V44: 1.0155085 | W44: 1.0142644 | X44: 1.0089771 | Y44: 1.0068867 | Z44: 0.99956986 | AA44: 0.99682261 | AB44: 0.98628166 | AC44: 0.98163636 | AD44: 102
B45: Omtanken Vårdcentral Grimmered | C45: 0.85812144 | D45: 0.85414313 | E45: 0.86510758 | F45: 0.87464203 | G45: 0.88616937 | H45: 0.89976884 | I45: 0.90394198 | J45: 0.90588572 | K45: 0.90158835 | L45: 0.89516811 | M45: 0.89103144 | N45: 0.90164625 | O45: 0.91476237 | P45: 0.91124103 | Q45: 0.91959553 | R45: 0.92111332 | S45: 0.92637996 | T45: 0.9231271 | U45: 0.9236994 | V45: 0.93016302 | W45: 0.9238617 | X45: 0.91179798 | Y45: 0.90559317 | Z45: 0.90304055 | AA45: 0.9001268 | AB45: 0.89803686 | AC45: 0.89683373 | AD45: 103
B46: Omtanken Vårdcentral Kviberg | C46: 0.93273453 | D46: 0.89610953 | E46: 0.89851149 | F46: 0.90611775 | G46: 0.9063587 | H46: 0.90463241 | I46: 0.91076933 | J46: 0.91121188 | K46: 0.91352088 | L46: 0.90918632 | M46: 0.90704513 | N46: 0.91450321 | O46: 0.91709344 | P46: 0.90472032 | Q46: 0.9067436 | R46: 0.90946114 | S46: 0.90698755 | T46: 0.91597037 | U46: 0.91951964 | V46: 0.91515712 | W46: 0.90967505 | X46: 0.90348776 | Y46: 0.89921768 | Z46: 0.88976982 | AA46: 0.89427953 | AB46: 0.8843176 | AC46: 0.88896177 | AD46: 110
B47: Omtanken Vårdcentral Kållered | C47: 0.8982267 | D47: 0.88447832 | E47: 0.88734242 | F47: 0.87404359 | G47: 0.87865509 | H47: 0.88715543 | I47: 0.88529578 | J47: 0.88440662 | K47: 0.88972724 | L47: 0.88141999 | M47: 0.88441493 | N47: 0.86983088 | O47: 0.89155218 | P47: 0.8898071 | Q47: 0.8885957 | R47: 0.88578321 | S47: 0.88889532 | T47: 0.8942587 | U47: 0.90540079 | V47: 0.90406458 | W47: 0.90861118 | X47: 0.92013724 | Y47: 0.92467783 | Z47: 0.92961752 | AA47: 0.92403522 | AB47: 0.92867449 | AC47: 0.92849587 | AD47: 109
B48: Omtanken Vårdcentral Landala | C48: 0.84229944 | D48: 0.81695126 | E48: 0.81664183 | F48: 0.81722325 | G48: 0.81607222 | H48: 0.81008918 | I48: 0.80676386 | J48: 0.80846341 | K48: 0.81159899 | L48: 0.81165044 | M48: 0.81641427 | N48: 0.82172091 | O48: 0.83185313 | P48: 0.82278172 | Q48: 0.80043846 | R48: 0.80252682 | S48: 0.80399649 | T48: 0.81155184 | U48: 0.81693363 | V48: 0.82734074 | W48: 0.8226776 | X48: 0.82243669 | Y48: 0.82525825 | Z48: 0.82305428 | AA48: 0.84146869 | AB48: 0.83825037 | AC48: 0.83185879 | AD48: 106
B49: Omtanken Vårdcentral Majorna | C49: 0.97837355 | D49: 0.97352902 | E49: 0.97764036 | F49: 0.97655905 | G49: 0.97760947 | H49: 0.97259952 | I49: 0.96958176 | J49: 0.97107264 | K49: 0.97128505 | L49: 0.95991971 | M49: 0.9625567 | N49: 0.96688841 | O49: 0.97065946 | P49: 0.96202884 | Q49: 0.95964477 | R49: 0.95807036 | S49: 0.96221091 | T49: 0.96873118 | U49: 0.973038 | V49: 0.968211 | W49: 0.96487508 | X49: 0.96255103 | Y49: 0.96022055 | Z49: 0.96018221 | AA49: 0.96873762 | AB49: 0.97544556 | AC49: 0.97256772 | AD49: 104
B50: Omtanken Vårdcentral Olskroken | C50: 0.97906872 | D50: 0.94615139 | E50: 0.943946 | F50: 0.9458501 | G50: 0.96440348 | H50: 0.96873082 | I50: 0.95873464 | J50: 0.96281542 | K50: 0.95624116 | L50: 0.95565308 | M50: 0.9644707 | N50: 0.97728051 | O50: 0.98476892 | P50: 0.96675369 | Q50: 0.95430093 | R50: 0.95760649 | S50: 0.96319403 | T50: 0.96382324 | U50: 0.96306225 | V50: 0.95493134 | W50: 0.93935504 | X50: 0.93364533 | Y50: 0.92603769 | Z50: 0.92650162 | AA50: 0.91961315 | AB50: 0.92311191 | AC50: 0.92660701 | AD50: 111
... B52: Omtanken Vårdcentral Åby | C52: 0.98115622 | D52: 0.97595562 | E52: 0.97653157 | F52: 0.97096849 | G52: 0.97927606 | H52: 0.97457087 | I52: 0.9766938 | J52: 0.97348262 | K52: 0.97761979 | L52: 0.98732781 | M52: 0.98651884 | N52: 0.98948441 | O52: 0.99477658 | P52: 1.000379 | Q52: 1.0036982 | R52: 0.99940755 | S52: 0.99308106 | T52: 0.99315521 | U52: 0.99694954 | V52: 0.99271879 | W52: 0.98821543 | X52: 0.99255293 | Y52: 0.99678712 | Z52: 0.99190725 | AA52: 0.9832571 | AB52: 0.97569731 | AC52: 0.96885556 | AD52: 108
C53: =AVERAGE(C39:C52) -> 0.88410202 | D53: =AVERAGE(D39:D52) -> 0.86215517 | E53: =AVERAGE(E39:E52) -> 0.86503876 | F53: =AVERAGE(F39:F52) -> 0.86652745 | G53: =AVERAGE(G39:G52) -> 0.86926466 | H53: =AVERAGE(H39:H52) -> 0.87147942 | I53: =AVERAGE(I39:I52) -> 0.87135901 | J53: =AVERAGE(J39:J52) -> 0.8726749 | ... AC53: =AVERAGE(AC39:AC52) -> 0.92737586
B55: Huvudintäkter (VGR) | C55: 202312 | D55: 202401 | E55: 202402 | F55: 202403 | G55: 202404 | H55: 202405 | I55: 202406 | J55: 202407 | K55: 202408 | L55: 202409 | M55: 202410 | N55: 202411 | O55: 202412 | P55: 202501 | Q55: 202502 | R55: 202503 | S55: 202504 | T55: 202505 | U55: 202506 | V55: 202507 | W55: 202508 | X55: 202509 | Y55: 202510 | Z55: 202511 | AA55: 202512 | AB55: 202601 | AC55: 202602
B56: Citysjukhuset Plus 7 vårdcentral | C56: ='Resultat-VC (3)'!E360 -> 1761650 | D56: ='Resultat-VC (3)'!F360 -> 1588915 | E56: ='Resultat-VC (3)'!G360 -> 1583472 | F56: ='Resultat-VC (3)'!H360 -> 1623341 | G56: ='Resultat-VC (3)'!I360 -> 1634285 | H56: ='Resultat-VC (3)'!J360 -> 1631728 | I56: ='Resultat-VC (3)'!K360 -> 1639794 | J56: ='Resultat-VC (3)'!L360 -> 1644169 | ... AB56: ='Resultat-VC (3)'!AD360 -> 2130950.2 | AC56: 2207769
B57: Kvarterskliniken Avenyn | C57: ='Resultat-VC (3)'!E280 -> 2656507.2 | D57: ='Resultat-VC (3)'!F280 -> 2181923 | E57: ='Resultat-VC (3)'!G280 -> 2191660.3 | F57: ='Resultat-VC (3)'!H280 -> 2232170.4 | G57: ='Resultat-VC (3)'!I280 -> 2210154.6 | H57: ='Resultat-VC (3)'!J280 -> 2242240.5 | I57: ='Resultat-VC (3)'!K280 -> 2248417.8 | J57: ='Resultat-VC (3)'!L280 -> 2202617.9 | ... AB57: ='Resultat-VC (3)'!AD280 -> 2717880.9 | AC57: 2595185
B58: Kvarterskliniken Husaren | C58: ='Resultat-VC (3)'!E332 -> 1502318 | D58: ='Resultat-VC (3)'!F332 -> 1448774.2 | E58: ='Resultat-VC (3)'!G332 -> 1384729 | F58: ='Resultat-VC (3)'!H332 -> 1432301.2 | G58: ='Resultat-VC (3)'!I332 -> 1414515.6 | H58: ='Resultat-VC (3)'!J332 -> 1411702.4 | I58: ='Resultat-VC (3)'!K332 -> 1388974.7 | J58: ='Resultat-VC (3)'!L332 -> 1378302.8 | ... AB58: ='Resultat-VC (3)'!AD332 -> 1614409.7 | AC58: 1511153
B59: Kvarterskliniken Karlastaden | C59: ='Resultat-VC (3)'!E7 -> 0 | D59: ='Resultat-VC (3)'!F7 -> 0 | E59: ='Resultat-VC (3)'!G7 -> 0 | F59: ='Resultat-VC (3)'!H7 -> 0 | G59: ='Resultat-VC (3)'!I7 -> 0 | H59: ='Resultat-VC (3)'!J7 -> 0 | I59: ='Resultat-VC (3)'!K7 -> 0 | J59: ='Resultat-VC (3)'!L7 -> 0 | ... AB59: ='Resultat-VC (3)'!AD7 -> 520984.24 | AC59: 526087
B60: Kvarterskliniken Lorensberg | C60: ='Resultat-VC (3)'!E308 -> 576629.42 | D60: ='Resultat-VC (3)'!F308 -> 538419.9 | E60: ='Resultat-VC (3)'!G308 -> 536473.77 | F60: ='Resultat-VC (3)'!H308 -> 550570.62 | G60: ='Resultat-VC (3)'!I308 -> 543463.78 | H60: ='Resultat-VC (3)'!J308 -> 554797.07 | I60: ='Resultat-VC (3)'!K308 -> 561980.08 | J60: ='Resultat-VC (3)'!L308 -> 561435.34 | ... AB60: ='Resultat-VC (3)'!AD308 -> 584364.66 | AC60: 563916
B61: Omtanken Vårdcentral Frölunda Torg | C61: ='Resultat-VC (3)'!E33 -> 3387788.5 | D61: ='Resultat-VC (3)'!F33 -> 3257986.8 | E61: ='Resultat-VC (3)'!G33 -> 3221008.8 | F61: ='Resultat-VC (3)'!H33 -> 3302493.1 | G61: ='Resultat-VC (3)'!I33 -> 3274832.3 | H61: ='Resultat-VC (3)'!J33 -> 3270634.9 | I61: ='Resultat-VC (3)'!K33 -> 3300053.1 | J61: ='Resultat-VC (3)'!L33 -> 3298555.5 | ... AB61: ='Resultat-VC (3)'!AD33 -> 3339426.4 | AC61: 3445724
B62: Omtanken Vårdcentral Grimmered | C62: ='Resultat-VC (3)'!E61 -> 2665355.6 | D62: ='Resultat-VC (3)'!F61 -> 2508673.7 | E62: ='Resultat-VC (3)'!G61 -> 2481925.4 | F62: ='Resultat-VC (3)'!H61 -> 2551115.3 | G62: ='Resultat-VC (3)'!I61 -> 2500798.5 | H62: ='Resultat-VC (3)'!J61 -> 2586789.5 | I62: ='Resultat-VC (3)'!K61 -> 2585325.9 | J62: ='Resultat-VC (3)'!L61 -> 2563245.6 | ... AB62: ='Resultat-VC (3)'!AD61 -> 2682738.7 | AC62: 2923423
B63: Omtanken Vårdcentral Kviberg | C63: ='Resultat-VC (3)'!E224 -> 1424083.9 | D63: ='Resultat-VC (3)'!F224 -> 1399564.4 | E63: ='Resultat-VC (3)'!G224 -> 1390109.3 | F63: ='Resultat-VC (3)'!H224 -> 1468569.4 | G63: ='Resultat-VC (3)'!I224 -> 1463536.7 | H63: ='Resultat-VC (3)'!J224 -> 1501030.3 | I63: ='Resultat-VC (3)'!K224 -> 1365204.9 | J63: ='Resultat-VC (3)'!L224 -> 1300562.4 | ... AB63: ='Resultat-VC (3)'!AD224 -> 1442578.6 | AC63: 1404497
B64: Omtanken Vårdcentral Kållered | C64: ='Resultat-VC (3)'!E200 -> 485839.86 | D64: ='Resultat-VC (3)'!F200 -> 478426.45 | E64: ='Resultat-VC (3)'!G200 -> 471301.48 | F64: ='Resultat-VC (3)'!H200 -> 482720.73 | G64: ='Resultat-VC (3)'!I200 -> 474241.52 | H64: ='Resultat-VC (3)'!J200 -> 471309.34 | I64: ='Resultat-VC (3)'!K200 -> 476785.22 | J64: ='Resultat-VC (3)'!L200 -> 480948.07 | ... AB64: ='Resultat-VC (3)'!AD200 -> 493036.77 | AC64: 503351
B65: Omtanken Vårdcentral Landala | C65: ='Resultat-VC (3)'!E144 -> 1769766.3 | D65: ='Resultat-VC (3)'!F144 -> 1754001.8 | E65: ='Resultat-VC (3)'!G144 -> 1744358 | F65: ='Resultat-VC (3)'!H144 -> 1743508.2 | G65: ='Resultat-VC (3)'!I144 -> 1739666.9 | H65: ='Resultat-VC (3)'!J144 -> 1747620.1 | I65: ='Resultat-VC (3)'!K144 -> 1783600.8 | J65: ='Resultat-VC (3)'!L144 -> 1775319.4 | ... AB65: ='Resultat-VC (3)'!AD144 -> 1799178.6 | AC65: 2022439
B66: Omtanken Vårdcentral Majorna | C66: ='Resultat-VC (3)'!E89 -> 2325319 | D66: ='Resultat-VC (3)'!F89 -> 2282442.6 | E66: ='Resultat-VC (3)'!G89 -> 2278606.3 | F66: ='Resultat-VC (3)'!H89 -> 2326465.4 | G66: ='Resultat-VC (3)'!I89 -> 2320123.4 | H66: ='Resultat-VC (3)'!J89 -> 2310671.8 | I66: ='Resultat-VC (3)'!K89 -> 2346140.1 | J66: ='Resultat-VC (3)'!L89 -> 2292339.2 | ... AB66: ='Resultat-VC (3)'!AD89 -> 2513531.2 | AC66: 2549879
B67: Omtanken Vårdcentral Olskroken | C67: ='Resultat-VC (3)'!E252 -> 1418017.1 | D67: ='Resultat-VC (3)'!F252 -> 1328306.7 | E67: ='Resultat-VC (3)'!G252 -> 1329298.9 | F67: ='Resultat-VC (3)'!H252 -> 1424141.2 | G67: ='Resultat-VC (3)'!I252 -> 1438573.6 | H67: ='Resultat-VC (3)'!J252 -> 1491057.5 | I67: ='Resultat-VC (3)'!K252 -> 1558532.9 | J67: ='Resultat-VC (3)'!L252 -> 1545614.3 | ... AB67: ='Resultat-VC (3)'!AD252 -> 2083294.8 | AC67: 2076726
B68: Omtanken Vårdcentral Pedagogen Park | C68: ='Resultat-VC (3)'!E144 -> 1769766.3 | D68: ='Resultat-VC (3)'!F144 -> 1754001.8 | E68: ='Resultat-VC (3)'!G144 -> 1744358 | F68: ='Resultat-VC (3)'!H144 -> 1743508.2 | G68: ='Resultat-VC (3)'!I144 -> 1739666.9 | H68: ='Resultat-VC (3)'!J144 -> 1747620.1 | I68: ='Resultat-VC (3)'!K144 -> 1783600.8 | J68: ='Resultat-VC (3)'!L144 -> 1775319.4 | ... AB68: ='Resultat-VC (3)'!AD144 -> 1799178.6 | AC68: 1816398
B69: Omtanken Vårdcentral Åby | C69: ='Resultat-VC (3)'!E172 -> 1980180.9 | D69: ='Resultat-VC (3)'!F172 -> 1861016.2 | E69: ='Resultat-VC (3)'!G172 -> 1863382.4 | F69: ='Resultat-VC (3)'!H172 -> 1857179 | G69: ='Resultat-VC (3)'!I172 -> 1875873.3 | H69: ='Resultat-VC (3)'!J172 -> 1876371.7 | I69: ='Resultat-VC (3)'!K172 -> 1857390 | J69: ='Resultat-VC (3)'!L172 -> 1859294.4 | ... AB69: ='Resultat-VC (3)'!AD172 -> 1895541.5 | AC69: 1965258
C70: =SUM(C56:C69) -> 23723222 | D70: =SUM(D56:D69) -> 22382453 | E70: =SUM(E56:E69) -> 22220684 | F70: =SUM(F56:F69) -> 22738084 | G70: =SUM(G56:G69) -> 22629732 | H70: =SUM(H56:H69) -> 22843573 | I70: =SUM(I56:I69) -> 22895801 | J70: =SUM(J56:J69) -> 22677723 | ... AC70: =SUM(AC56:AC69) -> 26111805
B72: Medical staff | C72: 202312 | D72: 202401 | E72: 202402 | F72: 202403 | G72: 202404 | H72: 202405 | I72: 202406 | J72: 202407 | K72: 202408 | L72: 202409 | M72: 202410 | N72: 202411 | O72: 202412 | P72: 202501 | Q72: 202502 | R72: 202503 | S72: 202504 | T72: 202505 | U72: 202506 | V72: 202507 | W72: 202508 | X72: 202509 | Y72: 202510 | Z72: 202511 | AA72: 202512 | AB72: 202601 | AC72: 202602
B73: Citysjukhuset Plus 7 vårdcentral | C73: ='Resultat-VC (3)'!E365 -> -1013138.4 | D73: ='Resultat-VC (3)'!F365 -> -842467.73 | E73: ='Resultat-VC (3)'!G365 -> -956713.42 | F73: ='Resultat-VC (3)'!H365 -> -776270.84 | G73: ='Resultat-VC (3)'!I365 -> -1055804 | H73: ='Resultat-VC (3)'!J365 -> -910145.03 | I73: ='Resultat-VC (3)'!K365 -> -792824.99 | J73: ='Resultat-VC (3)'!L365 -> -886763.21 | ... AB73: ='Resultat-VC (3)'!AD365 -> -1148624.4 | AC73: -1052367
B74: Kvarterskliniken Avenyn | C74: ='Resultat-VC (3)'!E294 -> -185716 | D74: ='Resultat-VC (3)'!F294 -> 0 | E74: ='Resultat-VC (3)'!G294 -> 0 | F74: ='Resultat-VC (3)'!H294 -> 0 | G74: ='Resultat-VC (3)'!I294 -> 0 | H74: ='Resultat-VC (3)'!J294 -> 0 | I74: ='Resultat-VC (3)'!K294 -> 0 | J74: ='Resultat-VC (3)'!L294 -> 0 | ... AB74: ='Resultat-VC (3)'!AD294 -> 0 | AC74: -1722429
B75: Kvarterskliniken Husaren | C75: ='Resultat-VC (3)'!E337 -> -766169.5 | D75: ='Resultat-VC (3)'!F337 -> -845027.87 | E75: ='Resultat-VC (3)'!G337 -> -802764.12 | F75: ='Resultat-VC (3)'!H337 -> -819760.24 | G75: ='Resultat-VC (3)'!I337 -> -825608.08 | H75: ='Resultat-VC (3)'!J337 -> -823604.46 | I75: ='Resultat-VC (3)'!K337 -> -697577.94 | J75: ='Resultat-VC (3)'!L337 -> -734404.87 | ... AB75: ='Resultat-VC (3)'!AD337 -> -890994.91 | AC75: -894718
B76: Kvarterskliniken Karlastaden | C76: ='Resultat-VC (3)'!E12 -> 0 | D76: ='Resultat-VC (3)'!F12 -> 0 | E76: ='Resultat-VC (3)'!G12 -> 0 | F76: ='Resultat-VC (3)'!H12 -> 0 | G76: ='Resultat-VC (3)'!I12 -> -90679.8 | H76: ='Resultat-VC (3)'!J12 -> -101126.21 | I76: ='Resultat-VC (3)'!K12 -> -99615.21 | J76: ='Resultat-VC (3)'!L12 -> -100860.21 | ... AB76: ='Resultat-VC (3)'!AD12 -> -548991.86 | AC76: -662683
B77: Kvarterskliniken Lorensberg
B78: Omtanken Vårdcentral Frölunda Torg | C78: ='Resultat-VC (3)'!E38 -> -1655124.9 | D78: ='Resultat-VC (3)'!F38 -> -1620790.8 | E78: ='Resultat-VC (3)'!G38 -> -1702474.1 | F78: ='Resultat-VC (3)'!H38 -> -1588865.5 | G78: ='Resultat-VC (3)'!I38 -> -1738137.5 | H78: ='Resultat-VC (3)'!J38 -> -1844514.8 | I78: ='Resultat-VC (3)'!K38 -> -1805177.3 | J78: ='Resultat-VC (3)'!L38 -> -1840020.4 | ... AB78: ='Resultat-VC (3)'!AD38 -> -1639769.8 | AC78: -1429586
B79: Omtanken Vårdcentral Grimmered | C79: ='Resultat-VC (3)'!E66 -> -1375917.1 | D79: ='Resultat-VC (3)'!F66 -> -1410584.6 | E79: ='Resultat-VC (3)'!G66 -> -1329656.8 | F79: ='Resultat-VC (3)'!H66 -> -1322354.1 | G79: ='Resultat-VC (3)'!I66 -> -1334150.8 | H79: ='Resultat-VC (3)'!J66 -> -1397043.1 | I79: ='Resultat-VC (3)'!K66 -> -1417157.3 | J79: ='Resultat-VC (3)'!L66 -> -1414838.6 | ... AB79: ='Resultat-VC (3)'!AD66 -> -1572593.3 | AC79: -1544955
B80: Omtanken Vårdcentral Kviberg | C80: ='Resultat-VC (3)'!E229 -> -932554.89 | D80: ='Resultat-VC (3)'!F229 -> -897587.93 | E80: ='Resultat-VC (3)'!G229 -> -940606.18 | F80: ='Resultat-VC (3)'!H229 -> -1001509.9 | G80: ='Resultat-VC (3)'!I229 -> -900785.7 | H80: ='Resultat-VC (3)'!J229 -> -1027435.8 | I80: ='Resultat-VC (3)'!K229 -> -1254894.9 | J80: ='Resultat-VC (3)'!L229 -> -1084219.3 | ... AB80: ='Resultat-VC (3)'!AD229 -> -924924.4 | AC80: -852142
B81: Omtanken Vårdcentral Kållered | C81: ='Resultat-VC (3)'!E205 -> -120835.69 | D81: ='Resultat-VC (3)'!F205 -> -119910.46 | E81: ='Resultat-VC (3)'!G205 -> -224884.31 | F81: ='Resultat-VC (3)'!H205 -> -161576.11 | G81: ='Resultat-VC (3)'!I205 -> -149698.69 | H81: ='Resultat-VC (3)'!J205 -> -149392.38 | I81: ='Resultat-VC (3)'!K205 -> -149843.06 | J81: ='Resultat-VC (3)'!L205 -> -135148.49 | ... AB81: ='Resultat-VC (3)'!AD205 -> -74910.68 | AC81: -69829
B82: Omtanken Vårdcentral Landala | C82: ='Resultat-VC (3)'!E122 -> -1014459.9 | D82: ='Resultat-VC (3)'!F122 -> -1211121.9 | E82: ='Resultat-VC (3)'!G122 -> -1195215.8 | F82: ='Resultat-VC (3)'!H122 -> -1054294.9 | G82: ='Resultat-VC (3)'!I122 -> -1172261.5 | H82: ='Resultat-VC (3)'!J122 -> -1137780.6 | I82: ='Resultat-VC (3)'!K122 -> -1191249.7 | J82: ='Resultat-VC (3)'!L122 -> -1244107 | ... AB82: ='Resultat-VC (3)'!AD122 -> -1174632.1 | AC82: -1195801
B83: Omtanken Vårdcentral Majorna | C83: ='Resultat-VC (3)'!E94 -> -1280079 | D83: ='Resultat-VC (3)'!F94 -> -1202898.6 | E83: ='Resultat-VC (3)'!G94 -> -1213219.9 | F83: ='Resultat-VC (3)'!H94 -> -1261114.4 | G83: ='Resultat-VC (3)'!I94 -> -1327154.5 | H83: ='Resultat-VC (3)'!J94 -> -1337064.5 | I83: ='Resultat-VC (3)'!K94 -> -1396818.2 | J83: ='Resultat-VC (3)'!L94 -> -1413507.8 | ... AB83: ='Resultat-VC (3)'!AD94 -> -1551672.6 | AC83: -1425514
B84: Omtanken Vårdcentral Olskroken | C84: ='Resultat-VC (3)'!E257 -> -802223.64 | D84: ='Resultat-VC (3)'!F257 -> -771760.16 | E84: ='Resultat-VC (3)'!G257 -> -673372.48 | F84: ='Resultat-VC (3)'!H257 -> -835829.84 | G84: ='Resultat-VC (3)'!I257 -> -786669.75 | H84: ='Resultat-VC (3)'!J257 -> -707269.17 | I84: ='Resultat-VC (3)'!K257 -> -827122.29 | J84: ='Resultat-VC (3)'!L257 -> -871621.76 | ... AB84: ='Resultat-VC (3)'!AD257 -> -1239252.1 | AC84: -1239593
B85: Omtanken Vårdcentral Pedagogen Park | C85: ='Resultat-VC (3)'!E149 -> -977057.62 | D85: ='Resultat-VC (3)'!F149 -> -869758.51 | E85: ='Resultat-VC (3)'!G149 -> -1029196.4 | F85: ='Resultat-VC (3)'!H149 -> -843568.85 | G85: ='Resultat-VC (3)'!I149 -> -910476.08 | H85: ='Resultat-VC (3)'!J149 -> -1249661.1 | I85: ='Resultat-VC (3)'!K149 -> -1099911.2 | J85: ='Resultat-VC (3)'!L149 -> -1307377.8 | ... AB85: ='Resultat-VC (3)'!AD149 -> -1231187 | AC85: -1184534
B86: Omtanken Vårdcentral Åby | C86: ='Resultat-VC (3)'!E177 -> -1168550.3 | D86: ='Resultat-VC (3)'!F177 -> -1330326.7 | E86: ='Resultat-VC (3)'!G177 -> -1166634.6 | F86: ='Resultat-VC (3)'!H177 -> -1194361.3 | G86: ='Resultat-VC (3)'!I177 -> -1323195.6 | H86: ='Resultat-VC (3)'!J177 -> -1292967.6 | I86: ='Resultat-VC (3)'!K177 -> -1326957.1 | J86: ='Resultat-VC (3)'!L177 -> -1290031.1 | ... AB86: ='Resultat-VC (3)'!AD177 -> -1386911.8 | AC86: -1297610
C87: =SUM(C73:C86) -> -11291827 | D87: =SUM(D73:D86) -> -11122235 | E87: =SUM(E73:E86) -> -11234738 | F87: =SUM(F73:F86) -> -10859506 | G87: =SUM(G73:G86) -> -11614622 | H87: =SUM(H73:H86) -> -11978005 | I87: =SUM(I73:I86) -> -12059149 | J87: =SUM(J73:J86) -> -12322901 | ... AC87: =SUM(AC73:AC86) -> -14571761
B89: Other direct costs | C89: 202312 | D89: 202401 | E89: 202402 | F89: 202403 | G89: 202404 | H89: 202405 | I89: 202406 | J89: 202407 | K89: 202408 | L89: 202409 | M89: 202410 | N89: 202411 | O89: 202412 | P89: 202501 | Q89: 202502 | R89: 202503 | S89: 202504 | T89: 202505 | U89: 202506 | V89: 202507 | W89: 202508 | X89: 202509 | Y89: 202510 | Z89: 202511 | AA89: 202512 | AB89: 202601 | AC89: 202602
B90: Citysjukhuset Plus 7 vårdcentral | C90: ='Resultat-VC (3)'!E366 -> -581360.23 | D90: ='Resultat-VC (3)'!F366 -> -596639.2 | E90: ='Resultat-VC (3)'!G366 -> -493413.56 | F90: ='Resultat-VC (3)'!H366 -> -445967.31 | G90: ='Resultat-VC (3)'!I366 -> -590627.24 | H90: ='Resultat-VC (3)'!J366 -> -554095.82 | I90: ='Resultat-VC (3)'!K366 -> -594438.99 | J90: ='Resultat-VC (3)'!L366 -> -476739.26 | ... AB90: ='Resultat-VC (3)'!AD366 -> -480587.23 | AC90: -529518
B91: Kvarterskliniken Avenyn | C91: ='Resultat-VC (3)'!E295 -> 72786 | D91: ='Resultat-VC (3)'!F295 -> -167588.11 | E91: ='Resultat-VC (3)'!G295 -> -206170.61 | F91: ='Resultat-VC (3)'!H295 -> -247994.06 | G91: ='Resultat-VC (3)'!I295 -> -154665.39 | H91: ='Resultat-VC (3)'!J295 -> -118281.29 | I91: ='Resultat-VC (3)'!K295 -> -274941.8 | J91: ='Resultat-VC (3)'!L295 -> -205139.42 | ... AB91: ='Resultat-VC (3)'!AD295 -> 199190.09 | AC91: -553032
B92: Kvarterskliniken Husaren | C92: ='Resultat-VC (3)'!E338 -> -540870.08 | D92: ='Resultat-VC (3)'!F338 -> -393766.47 | E92: ='Resultat-VC (3)'!G338 -> -403969.1 | F92: ='Resultat-VC (3)'!H338 -> -455877.45 | G92: ='Resultat-VC (3)'!I338 -> -449839.78 | H92: ='Resultat-VC (3)'!J338 -> -462816.32 | I92: ='Resultat-VC (3)'!K338 -> -412256.59 | J92: ='Resultat-VC (3)'!L338 -> -375221.37 | ... AB92: ='Resultat-VC (3)'!AD338 -> -365152.95 | AC92: -325487
B93: Kvarterskliniken Karlastaden | C93: ='Resultat-VC (3)'!E13 -> 0 | D93: ='Resultat-VC (3)'!F13 -> 0 | E93: ='Resultat-VC (3)'!G13 -> 0 | F93: ='Resultat-VC (3)'!H13 -> 0 | G93: ='Resultat-VC (3)'!I13 -> 0 | H93: ='Resultat-VC (3)'!J13 -> 0 | I93: ='Resultat-VC (3)'!K13 -> 0 | J93: ='Resultat-VC (3)'!L13 -> 0 | ... AB93: ='Resultat-VC (3)'!AD13 -> -153486.87 | AC93: -118974
B94: Kvarterskliniken Lorensberg | C94: ='Resultat-VC (3)'!E313 -> -104173.3 | D94: ='Resultat-VC (3)'!F313 -> -80607.29 | E94: ='Resultat-VC (3)'!G313 -> -66610.9 | F94: ='Resultat-VC (3)'!H313 -> -80267.95 | G94: ='Resultat-VC (3)'!I313 -> -72602.05 | H94: ='Resultat-VC (3)'!J313 -> -83683.44 | I94: ='Resultat-VC (3)'!K313 -> -94539.06 | J94: ='Resultat-VC (3)'!L313 -> -72724.62 | ... AB94: ='Resultat-VC (3)'!AD313 -> -80681.15 | AC94: -78512
B95: Omtanken Vårdcentral Frölunda Torg | C95: ='Resultat-VC (3)'!E39 -> -997354.58 | D95: ='Resultat-VC (3)'!F39 -> -897635.13 | E95: ='Resultat-VC (3)'!G39 -> -911545.79 | F95: ='Resultat-VC (3)'!H39 -> -1009142.3 | G95: ='Resultat-VC (3)'!I39 -> -1037026.5 | H95: ='Resultat-VC (3)'!J39 -> -997977.35 | I95: ='Resultat-VC (3)'!K39 -> -933865.22 | J95: ='Resultat-VC (3)'!L39 -> -864029.5 | ... AB95: ='Resultat-VC (3)'!AD39 -> -822431.49 | AC95: -914534
B96: Omtanken Vårdcentral Grimmered | C96: ='Resultat-VC (3)'!E67 -> -734675.75 | D96: ='Resultat-VC (3)'!F67 -> -735274.68 | E96: ='Resultat-VC (3)'!G67 -> -814770.96 | F96: ='Resultat-VC (3)'!H67 -> -692110.81 | G96: ='Resultat-VC (3)'!I67 -> -804981.66 | H96: ='Resultat-VC (3)'!J67 -> -807608.58 | I96: ='Resultat-VC (3)'!K67 -> -694303.42 | J96: ='Resultat-VC (3)'!L67 -> -683840.68 | ... AB96: ='Resultat-VC (3)'!AD67 -> -596362.35 | AC96: -606824
B97: Omtanken Vårdcentral Kviberg | C97: ='Resultat-VC (3)'!E230 -> -322979.48 | D97: ='Resultat-VC (3)'!F230 -> -313590.78 | E97: ='Resultat-VC (3)'!G230 -> -349602.76 | F97: ='Resultat-VC (3)'!H230 -> -310292.58 | G97: ='Resultat-VC (3)'!I230 -> -367967.48 | H97: ='Resultat-VC (3)'!J230 -> -370816.02 | I97: ='Resultat-VC (3)'!K230 -> -303093.45 | J97: ='Resultat-VC (3)'!L230 -> -365476.06 | ... AB97: ='Resultat-VC (3)'!AD230 -> -310589.75 | AC97: -359521
B98: Omtanken Vårdcentral Kållered | C98: ='Resultat-VC (3)'!E206 -> -126571.43 | D98: ='Resultat-VC (3)'!F206 -> -130673.02 | E98: ='Resultat-VC (3)'!G206 -> -123926.3 | F98: ='Resultat-VC (3)'!H206 -> -122709.04 | G98: ='Resultat-VC (3)'!I206 -> -128275.66 | H98: ='Resultat-VC (3)'!J206 -> -112734.21 | I98: ='Resultat-VC (3)'!K206 -> -107810.26 | J98: ='Resultat-VC (3)'!L206 -> -119670 | ... AB98: ='Resultat-VC (3)'!AD206 -> -112904.31 | AC98: -86394
B99: Omtanken Vårdcentral Landala | C99: ='Resultat-VC (3)'!E123 -> -425737.78 | D99: ='Resultat-VC (3)'!F123 -> -437494.19 | E99: ='Resultat-VC (3)'!G123 -> -409351.92 | F99: ='Resultat-VC (3)'!H123 -> -448860.69 | G99: ='Resultat-VC (3)'!I123 -> -443064.73 | H99: ='Resultat-VC (3)'!J123 -> -473449.38 | I99: ='Resultat-VC (3)'!K123 -> -470814.86 | J99: ='Resultat-VC (3)'!L123 -> -344129.12 | ... AB99: ='Resultat-VC (3)'!AD123 -> -420671.67 | AC99: -462274
B100: Omtanken Vårdcentral Majorna | C100: ='Resultat-VC (3)'!E95 -> -648079.65 | D100: ='Resultat-VC (3)'!F95 -> -676955.66 | E100: ='Resultat-VC (3)'!G95 -> -602687.97 | F100: ='Resultat-VC (3)'!H95 -> -619019.73 | G100: ='Resultat-VC (3)'!I95 -> -604154.53 | H100: ='Resultat-VC (3)'!J95 -> -659552.72 | I100: ='Resultat-VC (3)'!K95 -> -544282.32 | J100: ='Resultat-VC (3)'!L95 -> -530760.63 | ... AB100: ='Resultat-VC (3)'!AD95 -> -544251.2 | AC100: -527720
B101: Omtanken Vårdcentral Olskroken | C101: ='Resultat-VC (3)'!E258 -> -376633.07 | D101: ='Resultat-VC (3)'!F258 -> -406621.68 | E101: ='Resultat-VC (3)'!G258 -> -366053 | F101: ='Resultat-VC (3)'!H258 -> -349152.51 | G101: ='Resultat-VC (3)'!I258 -> -367848.99 | H101: ='Resultat-VC (3)'!J258 -> -334374.26 | I101: ='Resultat-VC (3)'!K258 -> -332133.88 | J101: ='Resultat-VC (3)'!L258 -> -293907.65 | ... AB101: ='Resultat-VC (3)'!AD258 -> -578553.72 | AC101: -468876
B102: Omtanken Vårdcentral Pedagogen Park | C102: ='Resultat-VC (3)'!E150 -> -468890.02 | D102: ='Resultat-VC (3)'!F150 -> -473189.36 | E102: ='Resultat-VC (3)'!G150 -> -449463.25 | F102: ='Resultat-VC (3)'!H150 -> -513517.89 | G102: ='Resultat-VC (3)'!I150 -> -466757.53 | H102: ='Resultat-VC (3)'!J150 -> -429867.94 | I102: ='Resultat-VC (3)'!K150 -> -474982.75 | J102: ='Resultat-VC (3)'!L150 -> -407596.97 | ... AB102: ='Resultat-VC (3)'!AD150 -> -405460.48 | AC102: -401035
B103: Omtanken Vårdcentral Åby | C103: ='Resultat-VC (3)'!E178 -> -451816.75 | D103: ='Resultat-VC (3)'!F178 -> -524252.09 | E103: ='Resultat-VC (3)'!G178 -> -509606.6 | F103: ='Resultat-VC (3)'!H178 -> -540516.68 | G103: ='Resultat-VC (3)'!I178 -> -547006.55 | H103: ='Resultat-VC (3)'!J178 -> -557367.03 | I103: ='Resultat-VC (3)'!K178 -> -505583.49 | J103: ='Resultat-VC (3)'!L178 -> -528047.57 | ... AB103: ='Resultat-VC (3)'!AD178 -> -417628.64 | AC103: -508305
C104: =SUM(C90:C103) -> -5706356.1 | D104: =SUM(D90:D103) -> -5834287.7 | E104: =SUM(E90:E103) -> -5707172.7 | F104: =SUM(F90:F103) -> -5835429 | G104: =SUM(G90:G103) -> -6034818.1 | H104: =SUM(H90:H103) -> -5962624.4 | I104: =SUM(I90:I103) -> -5743046.1 | J104: =SUM(J90:J103) -> -5267282.9 | ... AC104: =SUM(AC90:AC103) -> -5941006
Y105: =Y104-X104 -> -805221.92 | Z105: =Z104-Y104 -> 400916.25 | AA105: =AA104-Z104 -> 342331.26

Sheet Data
A3: Intäkter / listad pat | B3: 202312 | C3: 202401 | D3: 202402 | E3: 202403 | F3: 202404 | G3: 202405 | H3: 202406 | I3: 202407 | J3: 202408 | K3: 202409 | L3: 202410 | M3: 202411 | N3: 202412 | O3: 202501 | P3: 202502 | Q3: 202503 | R3: 202504 | S3: 202505 | T3: 202506 | U3: 202507 | V3: 202508 | W3: 202509 | X3: 202510 | Y3: 202511 | Z3: 202512 | AA3: 202601 | AB3: 202602
A4: Citysjukhuset Plus 7 vårdcentral | B4: =Info!C56/Info!C5 -> 345.82843 | C4: =Info!D56/Info!D5 -> 310.27436 | D4: =Info!E56/Info!E5 -> 306.3401 | E4: =Info!F56/Info!F5 -> 313.32581 | F4: =Info!G56/Info!G5 -> 316.53787 | G4: =Info!H56/Info!H5 -> 314.51966 | H4: =Info!I56/Info!I5 -> 314.80015 | I4: =Info!J56/Info!J5 -> 316.73454 | ... AB4: =Info!AC56/Info!AC5 -> 352.79147
A5: Kvarterskliniken Avenyn | B5: =Info!C57/Info!C6 -> 478.04701 | C5: =Info!D57/Info!D6 -> 391.86835 | D5: =Info!E57/Info!E6 -> 392.91149 | E5: =Info!F57/Info!F6 -> 399.38636 | F5: =Info!G57/Info!G6 -> 394.10746 | G5: =Info!H57/Info!H6 -> 400.18571 | H5: =Info!I57/Info!I6 -> 402.94227 | I5: =Info!J57/Info!J6 -> 393.2544 | ... AB5: =Info!AC57/Info!AC6 -> 435.21466
A6: Kvarterskliniken Husaren | B6: =Info!C58/Info!C7 -> 349.05158 | C6: =Info!D58/Info!D7 -> 339.92825 | D6: =Info!E58/Info!E7 -> 328.0571 | E6: =Info!F58/Info!F7 -> 342.00125 | F6: =Info!G58/Info!G7 -> 338.72501 | G6: =Info!H58/Info!H7 -> 340.0054 | H6: =Info!I58/Info!I7 -> 335.1773 | I6: =Info!J58/Info!J7 -> 331.72148 | ... AB6: =Info!AC58/Info!AC7 -> 357.58471
A7: Kvarterskliniken Karlastaden | B7: 0 | C7: 0 | D7: 0 | E7: 0 | F7: 0 | G7: 0 | H7: 0 | I7: 0 | J7: 0 | K7: =Info!L59/Info!L8 -> 220.29344 | L7: =Info!M59/Info!M8 -> 244.05578 | M7: =Info!N59/Info!N8 -> 319.32757 | N7: =Info!O59/Info!O8 -> 287.5567 | O7: =Info!P59/Info!P8 -> 319.1643 | P7: =Info!Q59/Info!Q8 -> 318.91458 | Q7: =Info!R59/Info!R8 -> 323.82446 | R7: =Info!S59/Info!S8 -> 333.53291 | ... AB7: =Info!AC59/Info!AC8 -> 313.33353
A8: Kvarterskliniken Lorensberg | B8: =Info!C60/Info!C9 -> 355.7245 | C8: =Info!D60/Info!D9 -> 333.38693 | D8: =Info!E60/Info!E9 -> 333.42062 | E8: =Info!F60/Info!F9 -> 343.24852 | F8: =Info!G60/Info!G9 -> 339.87729 | G8: =Info!H60/Info!H9 -> 348.70966 | H8: =Info!I60/Info!I9 -> 356.36023 | I8: =Info!J60/Info!J9 -> 358.05825 | ... AB8: =Info!AC60/Info!AC9 -> 375.69354
A9: Omtanken Vårdcentral Frölunda Torg | B9: =Info!C61/Info!C10 -> 415.17016 | C9: =Info!D61/Info!D10 -> 400.24408 | D9: =Info!E61/Info!E10 -> 396.92036 | E9: =Info!F61/Info!F10 -> 407.61455 | F9: =Info!G61/Info!G10 -> 403.80176 | G9: =Info!H61/Info!H10 -> 403.88181 | H9: =Info!I61/Info!I10 -> 407.56492 | I9: =Info!J61/Info!J10 -> 408.3887 | ... AB9: =Info!AC61/Info!AC10 -> 430.23149
A10: Omtanken Vårdcentral Grimmered | B10: =Info!C62/Info!C11 -> 424.89329 | C10: =Info!D62/Info!D11 -> 398.2654 | D10: =Info!E62/Info!E11 -> 395.33695 | E10: =Info!F62/Info!F11 -> 404.29719 | F10: =Info!G62/Info!G11 -> 396.26026 | G10: =Info!H62/Info!H11 -> 408.8493 | H10: =Info!I62/Info!I11 -> 409.00584 | I10: =Info!J62/Info!J11 -> 402.33019 | ... AB10: =Info!AC62/Info!AC11 -> 419.4896
A11: Omtanken Vårdcentral Kviberg | B11: =Info!C63/Info!C12 -> 357.6303 | C11: =Info!D63/Info!D12 -> 348.06378 | D11: =Info!E63/Info!E12 -> 340.62957 | E11: =Info!F63/Info!F12 -> 355.06998 | F11: =Info!G63/Info!G12 -> 353.17005 | G11: =Info!H63/Info!H12 -> 362.04301 | H11: =Info!I63/Info!I12 -> 335.18412 | I11: =Info!J63/Info!J12 -> 322.08084 | ... AB11: =Info!AC63/Info!AC12 -> 324.21445
A12: Omtanken Vårdcentral Kållered | B12: =Info!C64/Info!C13 -> 309.84685 | C12: =Info!D64/Info!D13 -> 305.7038 | D12: =Info!E64/Info!E13 -> 301.92279 | E12: =Info!F64/Info!F13 -> 309.83359 | F12: =Info!G64/Info!G13 -> 305.56799 | G12: =Info!H64/Info!H13 -> 303.6787 | H12: =Info!I64/Info!I13 -> 303.10567 | I12: =Info!J64/Info!J13 -> 303.62883 | ... AB12: =Info!AC64/Info!AC13 -> 327.91596
A13: Omtanken Vårdcentral Landala | B13: =Info!C65/Info!C14 -> 267.41708 | C13: =Info!D65/Info!D14 -> 264.31612 | D13: =Info!E65/Info!E14 -> 261.40537 | E13: =Info!F65/Info!F14 -> 261.39554 | F13: =Info!G65/Info!G14 -> 261.6434 | G13: =Info!H65/Info!H14 -> 262.56311 | H13: =Info!I65/Info!I14 -> 268.13001 | I13: =Info!J65/Info!J14 -> 267.73027 | ... AB13: =Info!AC65/Info!AC14 -> 314.48282
A14: Omtanken Vårdcentral Majorna | B14: =Info!C66/Info!C15 -> 371.51605 | C14: =Info!D66/Info!D15 -> 364.95725 | D14: =Info!E66/Info!E15 -> 365.10276 | E14: =Info!F66/Info!F15 -> 370.98795 | F14: =Info!G66/Info!G15 -> 369.62297 | G14: =Info!H66/Info!H15 -> 367.23963 | H14: =Info!I66/Info!I15 -> 372.22595 | I14: =Info!J66/Info!J15 -> 363.57481 | ... AB14: =Info!AC66/Info!AC15 -> 400.16933
A15: Omtanken Vårdcentral Olskroken | B15: =Info!C67/Info!C16 -> 411.73551 | C15: =Info!D67/Info!D16 -> 381.04036 | D15: =Info!E67/Info!E16 -> 375.08433 | E15: =Info!F67/Info!F16 -> 393.40917 | F15: =Info!G67/Info!G16 -> 392.4096 | G15: =Info!H67/Info!H16 -> 400.06908 | H15: =Info!I67/Info!I16 -> 413.51363 | I15: =Info!J67/Info!J16 -> 403.87099 | ... AB15: =Info!AC67/Info!AC16 -> 428.63282
A16: Omtanken Vårdcentral Pedagogen Park | B16: =Info!C68/Info!C17 -> 305.76473 | C16: =Info!D68/Info!D17 -> 303.46051 | D16: =Info!E68/Info!E17 -> 301.63549 | E16: =Info!F68/Info!F17 -> 301.07205 | F16: =Info!G68/Info!G17 -> 298.45033 | G16: =Info!H68/Info!H17 -> 298.94288 | H16: =Info!I68/Info!I17 -> 304.52464 | I16: =Info!J68/Info!J17 -> 302.38791 | ... AB16: =Info!AC68/Info!AC17 -> 323.03006
A17: Omtanken Vårdcentral Åby | B17: =Info!C69/Info!C18 -> 388.88078 | C17: =Info!D69/Info!D18 -> 365.55023 | D17: =Info!E69/Info!E18 -> 366.44689 | E17: =Info!F69/Info!F18 -> 366.81394 | F17: =Info!G69/Info!G18 -> 370.94588 | G17: =Info!H69/Info!H18 -> 371.04444 | H17: =Info!I69/Info!I18 -> 367.50891 | I17: =Info!J69/Info!J18 -> 367.52213 | ... AB17: =Info!AC69/Info!AC18 -> 390.3969
A18: Medelvärde stor-gbg | B18: =AVERAGE(B4:B17) -> 341.53616 | C18: =AVERAGE(C4:C17) -> 321.93282 | D18: =AVERAGE(D4:D17) -> 318.94384 | E18: =AVERAGE(E4:E17) -> 326.31828 | F18: =AVERAGE(F4:F17) -> 324.3657 | G18: =AVERAGE(G4:G17) -> 327.2666 | H18: =AVERAGE(H4:H17) -> 327.86026 | I18: =AVERAGE(I4:I17) -> 324.37738 | ... AB18: =AVERAGE(AB4:AB17) -> 370.94152
A44: Medical staff cost / listad pat | B44: 202312 | C44: 202401 | D44: 202402 | E44: 202403 | F44: 202404 | G44: 202405 | H44: 202406 | I44: 202407 | J44: 202408 | K44: 202409 | L44: 202410 | M44: 202411 | N44: 202412 | O44: 202501 | P44: 202502 | Q44: 202503 | R44: 202504 | S44: 202505 | T44: 202506 | U44: 202507 | V44: 202508 | W44: 202509 | X44: 202510 | Y44: 202511 | Z44: 202512 | AA44: 202601 | AB44: 202602
A45: Citysjukhuset Plus 7 vårdcentral | B45: =(Info!C73/Info!C5)*-1 -> 198.88857 | C45: =(Info!D73/Info!D5)*-1 -> 164.51235 | D45: =(Info!E73/Info!E5)*-1 -> 185.08675 | E45: =(Info!F73/Info!F5)*-1 -> 149.83031 | F45: =(Info!G73/Info!G5)*-1 -> 204.49428 | G45: =(Info!H73/Info!H5)*-1 -> 175.43274 | H45: =(Info!I73/Info!I5)*-1 -> 152.20292 | I45: =(Info!J73/Info!J5)*-1 -> 170.82705 | ... AB45: =(Info!AC73/Info!AC5)*-1 -> 168.16347
A46: Kvarterskliniken Avenyn | B46: =(Info!C74/(Info!C6+Info!C9))*-1 -> 25.872945 | C46: =(Info!D74/(Info!D6+Info!D9))*-1 -> 0 | D46: =(Info!E74/(Info!E6+Info!E9))*-1 -> 0 | E46: =(Info!F74/(Info!F6+Info!F9))*-1 -> 0 | F46: =(Info!G74/(Info!G6+Info!G9))*-1 -> 0 | G46: =(Info!H74/(Info!H6+Info!H9))*-1 -> 0 | H46: =(Info!I74/(Info!I6+Info!I9))*-1 -> 0 | I46: =(Info!J74/(Info!J6+Info!J9))*-1 -> 0 | ... AB46: =(Info!AC74/(Info!AC6+Info!AC9))*-1 -> 230.76487
A47: Kvarterskliniken Husaren | B47: =(Info!C75/Info!C7)*-1 -> 178.01336 | C47: =(Info!D75/Info!D7)*-1 -> 198.27027 | D47: =(Info!E75/Info!E7)*-1 -> 190.1834 | E47: =(Info!F75/Info!F7)*-1 -> 195.74027 | F47: =(Info!G75/Info!G7)*-1 -> 197.70308 | G47: =(Info!H75/Info!H7)*-1 -> 198.36331 | H47: =(Info!I75/Info!I7)*-1 -> 168.33444 | I47: =(Info!J75/Info!J7)*-1 -> 176.75207 | ... AB47: =(Info!AC75/Info!AC7)*-1 -> 211.71746
A48: Omtanken Vårdcentral Frölunda Torg | B48: =(Info!C78/Info!C10)*-1 -> 202.83393 | C48: =(Info!D78/Info!D10)*-1 -> 199.11435 | D48: =(Info!E78/Info!E10)*-1 -> 209.79349 | E48: =(Info!F78/Info!F10)*-1 -> 196.10781 | F48: =(Info!G78/Info!G10)*-1 -> 214.32028 | G48: =(Info!H78/Info!H10)*-1 -> 227.77411 | H48: =(Info!I78/Info!I10)*-1 -> 222.94397 | I48: =(Info!J78/Info!J10)*-1 -> 227.80988 | ... AB48: =(Info!AC78/Info!AC10)*-1 -> 178.49744
A49: Omtanken Vårdcentral Grimmered | B49: =(Info!C79/Info!C11)*-1 -> 219.33957 | C49: =(Info!D79/Info!D11)*-1 -> 223.93787 | D49: =(Info!E79/Info!E11)*-1 -> 211.79624 | E49: =(Info!F79/Info!F11)*-1 -> 209.56484 | F49: =(Info!G79/Info!G11)*-1 -> 211.40086 | G49: =(Info!H79/Info!H11)*-1 -> 220.80656 | H49: =(Info!I79/Info!I11)*-1 -> 224.19827 | I49: =(Info!J79/Info!J11)*-1 -> 222.07481 | ... AB49: =(Info!AC79/Info!AC11)*-1 -> 221.68963
A50: Omtanken Vårdcentral Kviberg | B50: =(Info!C80/Info!C12)*-1 -> 234.19259 | C50: =(Info!D80/Info!D12)*-1 -> 223.22505 | D50: =(Info!E80/Info!E12)*-1 -> 230.48424 | E50: =(Info!F80/Info!F12)*-1 -> 242.14456 | F50: =(Info!G80/Info!G12)*-1 -> 217.37107 | G50: =(Info!H80/Info!H12)*-1 -> 247.81376 | H50: =(Info!I80/Info!I12)*-1 -> 308.10089 | I50: =(Info!J80/Info!J12)*-1 -> 268.50405 | ... AB50: =(Info!AC80/Info!AC12)*-1 -> 196.70868
A51: Omtanken Vårdcentral Landala | B51: =(Info!C82/Info!C14)*-1 -> 153.28799 | C51: =(Info!D82/Info!D14)*-1 -> 182.50782 | D51: =(Info!E82/Info!E14)*-1 -> 179.11222 | E51: =(Info!F82/Info!F14)*-1 -> 158.06521 | F51: =(Info!G82/Info!G14)*-1 -> 176.30644 | G51: =(Info!H82/Info!H14)*-1 -> 170.9406 | H51: =(Info!I82/Info!I14)*-1 -> 179.08144 | I51: =(Info!J82/Info!J14)*-1 -> 187.61981 | ... AB51: =(Info!AC82/Info!AC14)*-1 -> 185.94324
A52: Omtanken Vårdcentral Majorna | B52: =(Info!C83/Info!C15)*-1 -> 204.51814 | C52: =(Info!D83/Info!D15)*-1 -> 192.34068 | D52: =(Info!E83/Info!E15)*-1 -> 194.39511 | E52: =(Info!F83/Info!F15)*-1 -> 201.10259 | F52: =(Info!G83/Info!G15)*-1 -> 211.43134 | G52: =(Info!H83/Info!H15)*-1 -> 212.50231 | H52: =(Info!I83/Info!I15)*-1 -> 221.61164 | I52: =(Info!J83/Info!J15)*-1 -> 224.18839 | ... AB52: =(Info!AC83/Info!AC15)*-1 -> 223.71532
A53: Omtanken Vårdcentral Olskroken | B53: =(Info!C84/Info!C16)*-1 -> 232.93369 | C53: =(Info!D84/Info!D16)*-1 -> 221.38846 | D53: =(Info!E84/Info!E16)*-1 -> 190.00352 | E53: =(Info!F84/Info!F16)*-1 -> 230.89222 | F53: =(Info!G84/Info!G16)*-1 -> 214.58531 | G53: =(Info!H84/Info!H16)*-1 -> 189.76903 | H53: =(Info!I84/Info!I16)*-1 -> 219.45404 | I53: =(Info!J84/Info!J16)*-1 -> 227.75588 | ... AB53: =(Info!AC84/Info!AC16)*-1 -> 255.84995
A54: Omtanken Vårdcentral Pedagogen Park | B54: =(Info!C85/Info!C17)*-1 -> 168.80747 | C54: =(Info!D85/Info!D17)*-1 -> 150.47725 | D54: =(Info!E85/Info!E17)*-1 -> 177.96928 | E54: =(Info!F85/Info!F17)*-1 -> 145.66894 | F54: =(Info!G85/Info!G17)*-1 -> 156.19765 | G54: =(Info!H85/Info!H17)*-1 -> 213.76344 | H54: =(Info!I85/Info!I17)*-1 -> 187.7943 | I54: =(Info!J85/Info!J17)*-1 -> 222.684 | ... AB54: =(Info!AC85/Info!AC17)*-1 -> 210.65872
A55: Omtanken Vårdcentral Åby | B55: =(Info!C86+Info!C81)/(Info!C18+Info!C13)*-1 -> 193.6015 | C55: =(Info!D86+Info!D81)/(Info!D18+Info!D13)*-1 -> 217.88419 | D55: =(Info!E86+Info!E81)/(Info!E18+Info!E13)*-1 -> 209.3769 | E55: =(Info!F86+Info!F81)/(Info!F18+Info!F13)*-1 -> 204.79344 | F55: =(Info!G86+Info!G81)/(Info!G18+Info!G13)*-1 -> 222.8619 | G55: =(Info!H86+Info!H81)/(Info!H18+Info!H13)*-1 -> 218.24179 | H55: =(Info!I86+Info!I81)/(Info!I18+Info!I13)*-1 -> 222.84596 | I55: =(Info!J86+Info!J81)/(Info!J18+Info!J13)*-1 -> 214.53855 | ... AB55: =(Info!AC86+Info!AC81)/(Info!AC18+Info!AC13)*-1 -> 208.16547
A56: Medelvärde Stor-GBG | B56: =AVERAGE(B45:B55) -> 182.93543 | C56: =AVERAGE(C45:C55) -> 179.42348 | D56: =AVERAGE(D45:D55) -> 179.83647 | E56: =AVERAGE(E45:E55) -> 175.81002 | F56: =AVERAGE(F45:F55) -> 184.24293 | G56: =AVERAGE(G45:G55) -> 188.67342 | H56: =AVERAGE(H45:H55) -> 191.50617 | I56: =AVERAGE(I45:I55) -> 194.79586 | ... AB56: =AVERAGE(AB45:AB55) -> 208.35221
A57: Kvarterskliniken Karlastaden | B57: =(Info!C76/Info!C8)*-1 -> #DIV/0! | C57: =(Info!D76/Info!D8)*-1 -> #DIV/0! | D57: =(Info!E76/Info!E8)*-1 -> #DIV/0! | E57: =(Info!F76/Info!F8)*-1 -> #DIV/0! | F57: =(Info!G76/Info!G8)*-1 -> #DIV/0! | G57: =(Info!H76/Info!H8)*-1 -> #DIV/0! | H57: =(Info!I76/Info!I8)*-1 -> #DIV/0! | I57: =(Info!J76/Info!J8)*-1 -> #DIV/0! | ... AB57: =(Info!AC76/Info!AC8)*-1 -> 394.6891
A82: Other direct costs / listad pat | B82: 202312 | C82: 202401 | D82: 202402 | E82: 202403 | F82: 202404 | G82: 202405 | H82: 202406 | I82: 202407 | J82: 202408 | K82: 202409 | L82: 202410 | M82: 202411 | N82: 202412 | O82: 202501 | P82: 202502 | Q82: 202503 | R82: 202504 | S82: 202505 | T82: 202506 | U82: 202507 | V82: 202508 | W82: 202509 | X82: 202510 | Y82: 202511 | Z82: 202512 | AA82: 202601 | AB82: 202602
A83: Citysjukhuset Plus 7 vårdcentral | B83: =(Info!C90/Info!C5)*-1 -> 114.12647 | C83: =(Info!D90/Info!D5)*-1 -> 116.50834 | D83: =(Info!E90/Info!E5)*-1 -> 95.456289 | E83: =(Info!F90/Info!F5)*-1 -> 86.077458 | F83: =(Info!G90/Info!G5)*-1 -> 114.39613 | G83: =(Info!H90/Info!H5)*-1 -> 106.80336 | H83: =(Info!I90/Info!I5)*-1 -> 114.11768 | I83: =(Info!J90/Info!J5)*-1 -> 91.83958 | ... AB83: =(Info!AC90/Info!AC5)*-1 -> 84.614573
A84: Kvarterskliniken Avenyn | B84: =(Info!C91/Info!C6)*-1 -> -13.098075 | C84: =(Info!D91/Info!D6)*-1 -> 30.098439 | D84: =(Info!E91/Info!E6)*-1 -> 36.961386 | E84: =(Info!F91/Info!F6)*-1 -> 44.371812 | F84: =(Info!G91/Info!G6)*-1 -> 27.57942 | G84: =(Info!H91/Info!H6)*-1 -> 21.11035 | H84: =(Info!I91/Info!I6)*-1 -> 49.272724 | I84: =(Info!J91/Info!J6)*-1 -> 36.625499 | ... AB84: =(Info!AC91/Info!AC6)*-1 -> 92.743921
A85: Kvarterskliniken Husaren | B85: =(Info!C92/Info!C7)*-1 -> 125.66684 | C85: =(Info!D92/Info!D7)*-1 -> 92.390068 | D85: =(Info!E92/Info!E7)*-1 -> 95.704596 | E85: =(Info!F92/Info!F7)*-1 -> 108.85326 | F85: =(Info!G92/Info!G7)*-1 -> 107.72025 | G85: =(Info!H92/Info!H7)*-1 -> 111.46829 | H85: =(Info!I92/Info!I7)*-1 -> 99.482768 | I85: =(Info!J92/Info!J7)*-1 -> 90.305986 | ... AB85: =(Info!AC92/Info!AC7)*-1 -> 77.020114
A86: Kvarterskliniken Lorensberg | B86: =(Info!C94/Info!C9)*-1 -> 64.264837 | C86: =(Info!D94/Info!D9)*-1 -> 49.911635 | D86: =(Info!E94/Info!E9)*-1 -> 41.398943 | E86: =(Info!F94/Info!F9)*-1 -> 50.042363 | F86: =(Info!G94/Info!G9)*-1 -> 45.404659 | G86: =(Info!H94/Info!H9)*-1 -> 52.598014 | H86: =(Info!I94/Info!I9)*-1 -> 59.948675 | I86: =(Info!J94/Info!J9)*-1 -> 46.380497 | ... AB86: =(Info!AC94/Info!AC9)*-1 -> 52.306462
A87: Omtanken Vårdcentral Frölunda Torg | B87: =(Info!C95/Info!C10)*-1 -> 122.22483 | C87: =(Info!D95/Info!D10)*-1 -> 110.27459 | D87: =(Info!E95/Info!E10)*-1 -> 112.3285 | E87: =(Info!F95/Info!F10)*-1 -> 124.55472 | F87: =(Info!G95/Info!G10)*-1 -> 127.8701 | G87: =(Info!H95/Info!H10)*-1 -> 123.23751 | H87: =(Info!I95/Info!I10)*-1 -> 115.33472 | I87: =(Info!J95/Info!J10)*-1 -> 106.97406 | ... AB87: =(Info!AC95/Info!AC10)*-1 -> 114.18829
A88: Omtanken Vårdcentral Grimmered | B88: =(Info!C96/Info!C11)*-1 -> 117.11713 | C88: =(Info!D96/Info!D11)*-1 -> 116.7288 | D88: =(Info!E96/Info!E11)*-1 -> 129.78193 | E88: =(Info!F96/Info!F11)*-1 -> 109.68476 | F88: =(Info!G96/Info!G11)*-1 -> 127.55216 | G88: =(Info!H96/Info!H11)*-1 -> 127.64479 | H88: =(Info!I96/Info!I11)*-1 -> 109.84076 | I88: =(Info!J96/Info!J11)*-1 -> 107.33647 | ... AB88: =(Info!AC96/Info!AC11)*-1 -> 87.07476
A89: Omtanken Vårdcentral Kviberg | B89: =(Info!C97/Info!C12)*-1 -> 81.109864 | C89: =(Info!D97/Info!D12)*-1 -> 77.988257 | D89: =(Info!E97/Info!E12)*-1 -> 85.665954 | E89: =(Info!F97/Info!F12)*-1 -> 75.022384 | F89: =(Info!G97/Info!G12)*-1 -> 88.795241 | G89: =(Info!H97/Info!H12)*-1 -> 89.439465 | H89: =(Info!I97/Info!I12)*-1 -> 74.415284 | I89: =(Info!J97/Info!J12)*-1 -> 90.509178 | ... AB89: =(Info!AC97/Info!AC12)*-1 -> 82.991921
A90: Omtanken Vårdcentral Kållered | B90: =(Info!C98/Info!C13)*-1 -> 80.721575 | C90: =(Info!D98/Info!D13)*-1 -> 83.497137 | D90: =(Info!E98/Info!E13)*-1 -> 79.389045 | E90: =(Info!F98/Info!F13)*-1 -> 78.760616 | F90: =(Info!G98/Info!G13)*-1 -> 82.651843 | G90: =(Info!H98/Info!H13)*-1 -> 72.638022 | H90: =(Info!I98/Info!I13)*-1 -> 68.537991 | I90: =(Info!J98/Info!J13)*-1 -> 75.549242 | ... AB90: =(Info!AC98/Info!AC13)*-1 -> 56.282736
A91: Omtanken Vårdcentral Landala | B91: =(Info!C99/Info!C14)*-1 -> 64.330278 | C91: =(Info!D99/Info!D14)*-1 -> 65.927395 | D91: =(Info!E99/Info!E14)*-1 -> 61.344511 | E91: =(Info!F99/Info!F14)*-1 -> 67.295456 | F91: =(Info!G99/Info!G14)*-1 -> 66.636296 | G91: =(Info!H99/Info!H14)*-1 -> 71.131217 | H91: =(Info!I99/Info!I14)*-1 -> 70.77794 | I91: =(Info!J99/Info!J14)*-1 -> 51.897017 | ... AB91: =(Info!AC99/Info!AC14)*-1 -> 71.882133
A92: Omtanken Vårdcentral Majorna | B92: =(Info!C100/Info!C15)*-1 -> 103.54364 | C92: =(Info!D100/Info!D15)*-1 -> 108.24363 | D92: =(Info!E100/Info!E15)*-1 -> 96.569135 | E92: =(Info!F100/Info!F15)*-1 -> 98.711486 | F92: =(Info!G100/Info!G15)*-1 -> 96.248929 | G92: =(Info!H100/Info!H15)*-1 -> 104.82402 | H92: =(Info!I100/Info!I15)*-1 -> 86.352899 | I92: =(Info!J100/Info!J15)*-1 -> 84.180909 | ... AB92: =(Info!AC100/Info!AC15)*-1 -> 82.818581
A93: Omtanken Vårdcentral Olskroken | B93: =(Info!C101/Info!C16)*-1 -> 109.3592 | C93: =(Info!D101/Info!D16)*-1 -> 116.6442 | D93: =(Info!E101/Info!E16)*-1 -> 103.28809 | E93: =(Info!F101/Info!F16)*-1 -> 96.45097 | F93: =(Info!G101/Info!G16)*-1 -> 100.3407 | G93: =(Info!H101/Info!H16)*-1 -> 89.716732 | H93: =(Info!I101/Info!I16)*-1 -> 88.122547 | I93: =(Info!J101/Info!J16)*-1 -> 76.798445 | ... AB93: =(Info!AC101/Info!AC16)*-1 -> 96.775232
A94: Omtanken Vårdcentral Pedagogen Park | B94: =(Info!C102/Info!C17)*-1 -> 81.010715 | C94: =(Info!D102/Info!D17)*-1 -> 81.866671 | D94: =(Info!E102/Info!E17)*-1 -> 77.721468 | E94: =(Info!F102/Info!F17)*-1 -> 88.675167 | F94: =(Info!G102/Info!G17)*-1 -> 80.075061 | G94: =(Info!H102/Info!H17)*-1 -> 73.531977 | H94: =(Info!I102/Info!I17)*-1 -> 81.096594 | I94: =(Info!J102/Info!J17)*-1 -> 69.425476 | ... AB94: =(Info!AC102/Info!AC17)*-1 -> 71.32047
A95: Omtanken Vårdcentral Åby | B95: =(Info!C103/Info!C18)*-1 -> 88.730705 | C95: =(Info!D103/Info!D18)*-1 -> 102.97625 | D95: =(Info!E103/Info!E18)*-1 -> 100.21762 | E95: =(Info!F103/Info!F18)*-1 -> 106.75818 | F95: =(Info!G103/Info!G18)*-1 -> 108.16819 | G95: =(Info!H103/Info!H18)*-1 -> 110.21693 | H95: =(Info!I103/Info!I18)*-1 -> 100.03631 | I95: =(Info!J103/Info!J18)*-1 -> 104.37786 | ... AB95: =(Info!AC103/Info!AC18)*-1 -> 100.97437
A96: Kvarterskliniken Karlastaden | B96: 0 | C96: 0 | D96: 0 | E96: 0 | F96: 0 | G96: 0 | H96: 0 | I96: 0 | J96: 0 | K96: =(Info!L93/Info!L8)*-1 -> 425.8239 | L96: =(Info!M93/Info!M8)*-1 -> 277.36425 | M96: =(Info!N93/Info!N8)*-1 -> 146.70684 | N96: =(Info!O93/Info!O8)*-1 -> 81.788114 | O96: =(Info!P93/Info!P8)*-1 -> 197.26296 | P96: =(Info!Q93/Info!Q8)*-1 -> 108.91366 | Q96: =(Info!R93/Info!R8)*-1 -> 231.80464 | R96: =(Info!S93/Info!S8)*-1 -> -26.744588 | ... AB96: =(Info!AC93/Info!AC8)*-1 -> 70.860036
A97: Medelvärde Stor-GBG | B97: =AVERAGE(B83:B96) -> 81.364857 | C97: =AVERAGE(C83:C96) -> 82.3611 | D97: =AVERAGE(D83:D96) -> 79.701962 | E97: =AVERAGE(E83:E96) -> 81.089902 | F97: =AVERAGE(F83:F96) -> 83.81707 | G97: =AVERAGE(G83:G96) -> 82.454333 | H97: =AVERAGE(H83:H96) -> 79.809777 | I97: =AVERAGE(I83:I96) -> 73.728587 | ... AB97: =AVERAGE(AB83:AB96) -> 81.560972
A123: Stor-GBG AO | B123: 202312 | C123: 202401 | D123: 202402 | E123: 202403 | F123: 202404 | G123: 202405 | H123: 202406 | I123: 202407 | J123: 202408 | K123: 202409 | L123: 202410 | M123: 202411 | N123: 202412 | O123: 202501 | P123: 202502 | Q123: 202503 | R123: 202504 | S123: 202505 | T123: 202506 | U123: 202507 | V123: 202508 | W123: 202509 | X123: 202510 | Y123: 202511 | Z123: 202512 | AA123: 202601 | AB123: 202602
A124: Antal listade pat | B124: =Info!C19 -> 63760 | C124: =Info!D19 -> 63838 | D124: =Info!E19 -> 63938 | E124: =Info!F19 -> 64083 | F124: =Info!G19 -> 64141 | G124: =Info!H19 -> 64235 | H124: =Info!I19 -> 64209 | I124: =Info!J19 -> 64278 | ... AA124: =Info!AB19 -> 68799
A125: Antal listningpoäng | B125: =Info!C36 -> 19501.258 | C125: =Info!D36 -> 19548.719 | D125: =Info!E36 -> 19690.007 | E125: =Info!F36 -> 19786.079 | F125: =Info!G36 -> 19847.919 | G125: =Info!H36 -> 19933.757 | H125: =Info!I36 -> 19883.608 | I125: =Info!J36 -> 19871.158 | ... AB125: =Info!AC36 -> 21330.334
A126: ACG casemix | B126: =Info!C53 -> 0.88410202 | C126: =Info!D53 -> 0.86215517 | D126: =Info!E53 -> 0.86503876 | E126: =Info!F53 -> 0.86652745 | F126: =Info!G53 -> 0.86926466 | G126: =Info!H53 -> 0.87147942 | H126: =Info!I53 -> 0.87135901 | I126: =Info!J53 -> 0.8726749 | ... AA126: =Info!AB53 -> 0.92480374
A127: Huvudintäkter (VGR) | B127: =Info!C70 -> 23723222 | C127: =Info!D70 -> 22382453 | D127: =Info!E70 -> 22220684 | E127: =Info!F70 -> 22738084 | F127: =Info!G70 -> 22629732 | G127: =Info!H70 -> 22843573 | H127: =Info!I70 -> 22895801 | I127: =Info!J70 -> 22677723 | ... AA127: =Info!AB70 -> 25617095
A128: Medical staff | B128: =Info!C87*-1 -> 11291827 | C128: =Info!D87*-1 -> 11122235 | D128: =Info!E87*-1 -> 11234738 | E128: =Info!F87*-1 -> 10859506 | F128: =Info!G87*-1 -> 11614622 | G128: =Info!H87*-1 -> 11978005 | H128: =Info!I87*-1 -> 12059149 | I128: =Info!J87*-1 -> 12322901 | ... AA128: =Info!AB87*-1 -> 13384465
A129: Other direct costs | B129: =Info!C104*-1 -> 5706356.1 | C129: =Info!D104*-1 -> 5834287.7 | D129: =Info!E104*-1 -> 5707172.7 | E129: =Info!F104*-1 -> 5835429 | F129: =Info!G104*-1 -> 6034818.1 | G129: =Info!H104*-1 -> 5962624.4 | H129: =Info!I104*-1 -> 5743046.1 | I129: =Info!J104*-1 -> 5267282.9 | ... AA129: =Info!AB104*-1 -> 5089571.7
A130: Diff | B130: =Info!C20 -> 0 | C130: =Info!D20 -> 78 | D130: =Info!E20 -> 100 | E130: =Info!F20 -> 145 | F130: =Info!G20 -> 58 | G130: =Info!H20 -> 94 | H130: =Info!I20 -> -26 | I130: =Info!J20 -> 69 | ... AB130: =Info!AC20 -> -22
A153: ACG casemix | B153: 202312 | C153: 202401 | D153: 202402 | E153: 202403 | F153: 202404 | G153: 202405 | H153: 202406 | I153: 202407 | J153: 202408 | K153: 202409 | L153: 202410 | M153: 202411 | N153: 202412 | O153: 202501 | P153: 202502 | Q153: 202503 | R153: 202504 | S153: 202505 | T153: 202506 | U153: 202507 | V153: 202508 | W153: 202509 | X153: 202510 | Y153: 202511 | Z153: 202512 | AA153: 202601 | AB153: 202602
A154: Citysjukhuset Plus 7 vårdcentral | B154: =Info!C39 -> 1.0614071 | C154: =Info!D39 -> 0.97451976 | D154: =Info!E39 -> 0.98125772 | E154: =Info!F39 -> 0.98832216 | F154: =Info!G39 -> 0.99099207 | G154: =Info!H39 -> 0.9992378 | H154: =Info!I39 -> 1.007592 | I154: =Info!J39 -> 1.0228048 | ... AB154: =Info!AC39 -> 1.0059425
A155: Kvarterskliniken Avenyn | B155: =Info!C40 -> 1.075854 | C155: =Info!D40 -> 1.0382789 | D155: =Info!E40 -> 1.0379765 | E155: =Info!F40 -> 1.0339203 | F155: =Info!G40 -> 1.0373011 | G155: =Info!H40 -> 1.0422695 | H155: =Info!I40 -> 1.0397034 | I155: =Info!J40 -> 1.0388481 | ... AB155: =Info!AC40 -> 1.0086668
A156: Kvarterskliniken Husaren | B156: =Info!C41 -> 1.0128972 | C156: =Info!D41 -> 0.98877368 | D156: =Info!E41 -> 0.99337215 | E156: =Info!F41 -> 0.99566803 | F156: =Info!G41 -> 0.98475143 | G156: =Info!H41 -> 0.98425641 | H156: =Info!I41 -> 0.96612632 | I156: =Info!J41 -> 0.95385616 | ... AB156: =Info!AC41 -> 0.94237833
A157: Kvarterskliniken Karlastaden | B157: =Info!C42 -> 0 | C157: =Info!D42 -> 0 | D157: =Info!E42 -> 0 | E157: =Info!F42 -> 0 | F157: =Info!G42 -> 0 | G157: =Info!H42 -> 0 | H157: =Info!I42 -> 0 | I157: =Info!J42 -> 0 | ... AB157: =Info!AC42 -> 1.0042477
A158: Kvarterskliniken Lorensberg | B158: =Info!C43 -> 0.90236362 | C158: =Info!D43 -> 0.86693574 | D158: =Info!E43 -> 0.87198303 | E158: =Info!F43 -> 0.88203489 | F158: =Info!G43 -> 0.88721764 | G158: =Info!H43 -> 0.89133838 | H158: =Info!I43 -> 0.90970316 | I158: =Info!J43 -> 0.92034375 | ... AB158: =Info!AC43 -> 0.85321029
A159: Omtanken Vårdcentral Frölunda Torg | B159: =Info!C44 -> 0.99226622 | C159: =Info!D44 -> 0.9941307 | D159: =Info!E44 -> 0.99623528 | E159: =Info!F44 -> 1.0030491 | F159: =Info!G44 -> 1.0080654 | G159: =Info!H44 -> 1.0132702 | H159: =Info!I44 -> 1.0174282 | I159: =Info!J44 -> 1.0211185 | ... AB159: =Info!AC44 -> 0.98163636
A160: Omtanken Vårdcentral Grimmered | B160: =Info!C45 -> 0.85812144 | C160: =Info!D45 -> 0.85414313 | D160: =Info!E45 -> 0.86510758 | E160: =Info!F45 -> 0.87464203 | F160: =Info!G45 -> 0.88616937 | G160: =Info!H45 -> 0.89976884 | H160: =Info!I45 -> 0.90394198 | I160: =Info!J45 -> 0.90588572 | ... AB160: =Info!AC45 -> 0.89683373
A161: Omtanken Vårdcentral Kviberg | B161: =Info!C46 -> 0.93273453 | C161: =Info!D46 -> 0.89610953 | D161: =Info!E46 -> 0.89851149 | E161: =Info!F46 -> 0.90611775 | F161: =Info!G46 -> 0.9063587 | G161: =Info!H46 -> 0.90463241 | H161: =Info!I46 -> 0.91076933 | I161: =Info!J46 -> 0.91121188 | ... AB161: =Info!AC46 -> 0.88896177
A162: Omtanken Vårdcentral Kållered | B162: =Info!C47 -> 0.8982267 | C162: =Info!D47 -> 0.88447832 | D162: =Info!E47 -> 0.88734242 | E162: =Info!F47 -> 0.87404359 | F162: =Info!G47 -> 0.87865509 | G162: =Info!H47 -> 0.88715543 | H162: =Info!I47 -> 0.88529578 | I162: =Info!J47 -> 0.88440662 | ... AB162: =Info!AC47 -> 0.92849587
A163: Omtanken Vårdcentral Landala | B163: =Info!C48 -> 0.84229944 | C163: =Info!D48 -> 0.81695126 | D163: =Info!E48 -> 0.81664183 | E163: =Info!F48 -> 0.81722325 | F163: =Info!G48 -> 0.81607222 | G163: =Info!H48 -> 0.81008918 | H163: =Info!I48 -> 0.80676386 | I163: =Info!J48 -> 0.80846341 | ... AB163: =Info!AC48 -> 0.83185879
A164: Omtanken Vårdcentral Majorna | B164: =Info!C49 -> 0.97837355 | C164: =Info!D49 -> 0.97352902 | D164: =Info!E49 -> 0.97764036 | E164: =Info!F49 -> 0.97655905 | F164: =Info!G49 -> 0.97760947 | G164: =Info!H49 -> 0.97259952 | H164: =Info!I49 -> 0.96958176 | I164: =Info!J49 -> 0.97107264 | ... AB164: =Info!AC49 -> 0.97256772
A165: Omtanken Vårdcentral Olskroken | B165: =Info!C50 -> 0.97906872 | C165: =Info!D50 -> 0.94615139 | D165: =Info!E50 -> 0.943946 | E165: =Info!F50 -> 0.9458501 | F165: =Info!G50 -> 0.96440348 | G165: =Info!H50 -> 0.96873082 | H165: =Info!I50 -> 0.95873464 | I165: =Info!J50 -> 0.96281542 | ... AB165: =Info!AC50 -> 0.92660701
... A167: Omtanken Vårdcentral Åby | B167: =Info!C52 -> 0.98115622 | C167: =Info!D52 -> 0.97595562 | D167: =Info!E52 -> 0.97653157 | E167: =Info!F52 -> 0.97096849 | F167: =Info!G52 -> 0.97927606 | G167: =Info!H52 -> 0.97457087 | H167: =Info!I52 -> 0.9766938 | I167: =Info!J52 -> 0.97348262 | ... AB167: =Info!AC52 -> 0.96885556
A168: Medelvärde Stor-GBG | B168: =AVERAGE(B154:B167) -> 0.88410202 | C168: =AVERAGE(C154:C167) -> 0.86215517 | D168: =AVERAGE(D154:D167) -> 0.86503876 | E168: =AVERAGE(E154:E167) -> 0.86652745 | F168: =AVERAGE(F154:F167) -> 0.86926466 | G168: =AVERAGE(G154:G167) -> 0.87147942 | H168: =AVERAGE(H154:H167) -> 0.87135901 | I168: =AVERAGE(I154:I167) -> 0.8726749 | ... AB168: =AVERAGE(AB154:AB167) -> 0.92737586
A198: Antal listade pat | B198: 202312 | C198: 202401 | D198: 202402 | E198: 202403 | F198: 202404 | G198: 202405 | H198: 202406 | I198: 202407 | J198: 202408 | K198: 202409 | L198: 202410 | M198: 202411 | N198: 202412 | O198: 202501 | P198: 202502 | Q198: 202503 | R198: 202504 | S198: 202505 | T198: 202506 | U198: 202507 | V198: 202508 | W198: 202509 | X198: 202510 | Y198: 202511 | Z198: 202512 | AA198: 202601 | AB198: 202602
A199: Citysjukhuset Plus 7 vårdcentral | B199: =Info!C5 -> 5094 | C199: =Info!D5 -> 5121 | D199: =Info!E5 -> 5169 | E199: =Info!F5 -> 5181 | F199: =Info!G5 -> 5163 | G199: =Info!H5 -> 5188 | H199: =Info!I5 -> 5209 | I199: =Info!J5 -> 5191 | ... AB199: =Info!AC5 -> 6258
A200: Kvarterskliniken Avenyn | B200: =Info!C6 -> 5557 | C200: =Info!D6 -> 5568 | D200: =Info!E6 -> 5578 | E200: =Info!F6 -> 5589 | F200: =Info!G6 -> 5608 | G200: =Info!H6 -> 5603 | H200: =Info!I6 -> 5580 | I200: =Info!J6 -> 5601 | ... AB200: =Info!AC6 -> 5963
A201: Kvarterskliniken Husaren | B201: =Info!C7 -> 4304 | C201: =Info!D7 -> 4262 | D201: =Info!E7 -> 4221 | E201: =Info!F7 -> 4188 | F201: =Info!G7 -> 4176 | G201: =Info!H7 -> 4152 | H201: =Info!I7 -> 4144 | I201: =Info!J7 -> 4155 | ... AB201: =Info!AC7 -> 4226
A202: Kvarterskliniken Karlastaden | B202: =Info!C8 -> 0 | C202: =Info!D8 -> 0 | D202: =Info!E8 -> 0 | E202: =Info!F8 -> 0 | F202: =Info!G8 -> 0 | G202: =Info!H8 -> 0 | H202: =Info!I8 -> 0 | I202: =Info!J8 -> 0 | ... AB202: =Info!AC8 -> 1679
A203: Kvarterskliniken Lorensberg | B203: =Info!C9 -> 1621 | C203: =Info!D9 -> 1615 | D203: =Info!E9 -> 1609 | E203: =Info!F9 -> 1604 | F203: =Info!G9 -> 1599 | G203: =Info!H9 -> 1591 | H203: =Info!I9 -> 1577 | I203: =Info!J9 -> 1568 | ... AB203: =Info!AC9 -> 1501
A204: Omtanken Vårdcentral Frölunda Torg | B204: =Info!C10 -> 8160 | C204: =Info!D10 -> 8140 | D204: =Info!E10 -> 8115 | E204: =Info!F10 -> 8102 | F204: =Info!G10 -> 8110 | G204: =Info!H10 -> 8098 | H204: =Info!I10 -> 8097 | I204: =Info!J10 -> 8077 | ... AB204: =Info!AC10 -> 8009
A205: Omtanken Vårdcentral Grimmered | B205: =Info!C11 -> 6273 | C205: =Info!D11 -> 6299 | D205: =Info!E11 -> 6278 | E205: =Info!F11 -> 6310 | F205: =Info!G11 -> 6311 | G205: =Info!H11 -> 6327 | H205: =Info!I11 -> 6321 | I205: =Info!J11 -> 6371 | ... AB205: =Info!AC11 -> 6969
A206: Omtanken Vårdcentral Kviberg | B206: =Info!C12 -> 3982 | C206: =Info!D12 -> 4021 | D206: =Info!E12 -> 4081 | E206: =Info!F12 -> 4136 | F206: =Info!G12 -> 4144 | G206: =Info!H12 -> 4146 | H206: =Info!I12 -> 4073 | I206: =Info!J12 -> 4038 | ... AB206: =Info!AC12 -> 4332
A207: Omtanken Vårdcentral Kållered | B207: =Info!C13 -> 1568 | C207: =Info!D13 -> 1565 | D207: =Info!E13 -> 1561 | E207: =Info!F13 -> 1558 | F207: =Info!G13 -> 1552 | G207: =Info!H13 -> 1552 | H207: =Info!I13 -> 1573 | I207: =Info!J13 -> 1584 | ... AB207: =Info!AC13 -> 1535
A208: Omtanken Vårdcentral Landala | B208: =Info!C14 -> 6618 | C208: =Info!D14 -> 6636 | D208: =Info!E14 -> 6673 | E208: =Info!F14 -> 6670 | F208: =Info!G14 -> 6649 | G208: =Info!H14 -> 6656 | H208: =Info!I14 -> 6652 | I208: =Info!J14 -> 6631 | ... AB208: =Info!AC14 -> 6431
A209: Omtanken Vårdcentral Majorna | B209: =Info!C15 -> 6259 | C209: =Info!D15 -> 6254 | D209: =Info!E15 -> 6241 | E209: =Info!F15 -> 6271 | F209: =Info!G15 -> 6277 | G209: =Info!H15 -> 6292 | H209: =Info!I15 -> 6303 | I209: =Info!J15 -> 6305 | ... AB209: =Info!AC15 -> 6372
A210: Omtanken Vårdcentral Olskroken | B210: =Info!C16 -> 3444 | C210: =Info!D16 -> 3486 | D210: =Info!E16 -> 3544 | E210: =Info!F16 -> 3620 | F210: =Info!G16 -> 3666 | G210: =Info!H16 -> 3727 | H210: =Info!I16 -> 3769 | I210: =Info!J16 -> 3827 | ... AB210: =Info!AC16 -> 4845
... A212: Omtanken Vårdcentral Åby | B212: =Info!C18 -> 5092 | C212: =Info!D18 -> 5091 | D212: =Info!E18 -> 5085 | E212: =Info!F18 -> 5063 | F212: =Info!G18 -> 5057 | G212: =Info!H18 -> 5057 | H212: =Info!I18 -> 5054 | I212: =Info!J18 -> 5059 | ... AB212: =Info!AC18 -> 5034
A240: Total antallistade patienter | B240: 202312 | C240: 202401 | D240: 202402 | E240: 202403 | F240: 202404 | G240: 202405 | H240: 202406 | I240: 202407 | J240: 202408 | K240: 202409 | L240: 202410 | M240: 202411 | N240: 202412 | O240: 202501 | P240: 202502 | Q240: 202503 | R240: 202504 | S240: 202505 | T240: 202506 | U240: 202507 | V240: 202508 | W240: 202509 | X240: 202510 | Y240: 202511 | Z240: 202512 | AA240: 202601 | AB240: 202602
A241: Listning AO Stor-GBG | B241: =Info!C19 -> 63760 | C241: =Info!D19 -> 63838 | D241: =Info!E19 -> 63938 | E241: =Info!F19 -> 64083 | F241: =Info!G19 -> 64141 | G241: =Info!H19 -> 64235 | H241: =Info!I19 -> 64209 | I241: =Info!J19 -> 64278 | ... AB241: =Info!AC19 -> 68777
A264: ACG casemix | B264: 202312 | C264: 202401 | D264: 202402 | E264: 202403 | F264: 202404 | G264: 202405 | H264: 202406 | I264: 202407 | J264: 202408 | K264: 202409 | L264: 202410 | M264: 202411 | N264: 202412 | O264: 202501 | P264: 202502 | Q264: 202503 | R264: 202504 | S264: 202505 | T264: 202506 | U264: 202507 | V264: 202508 | W264: 202509 | X264: 202510 | Y264: 202511 | Z264: 202512 | AA264: 202601 | AB264: 202602
A265: Medelvärde AO Stor-GBG | B265: =Info!C53 -> 0.88410202 | C265: =Info!D53 -> 0.86215517 | D265: =Info!E53 -> 0.86503876 | E265: =Info!F53 -> 0.86652745 | F265: =Info!G53 -> 0.86926466 | G265: =Info!H53 -> 0.87147942 | H265: =Info!I53 -> 0.87135901 | I265: =Info!J53 -> 0.8726749 | ... AB265: =Info!AC53 -> 0.92737586
A293: Rehab poäng | C293: 202409 | D293: 202410 | E293: 202411 | F293: 202412 | G293: 202501 | H293: 202502 | I293: 202503 | J293: 202504 | K293: 202505 | L293: 202506 | M293: 202507 | N293: 202508 | O293: 202509 | P293: 202510 | Q293: 202511 | R293: 202512 | S293: 202601 | T293: 202602
A294: Frölunda Torg | B294: 102 | C294: 341 | D294: 996 | E294: 1088 | F294: 375 | G294: 1074 | H294: 1123 | I294: 871 | J294: 924 | K294: 842 | L294: 887 | M294: 958 | N294: 560 | O294: 1031 | P294: 1025 | Q294: 990 | R294: 778 | S294: 779 | T294: 900
A295: Grimmered | B295: 103 | C295: 270 | D295: 783 | E295: 1053 | F295: 420 | G295: 1052 | H295: 938 | I295: 938 | J295: 934 | K295: 1056 | L295: 952 | M295: 829 | N295: 503 | O295: 931 | P295: 1013 | Q295: 990 | R295: 748 | S295: 754 | T295: 884
A296: Olskroken | B296: 111 | C296: 146 | D296: 538 | E296: 637 | F296: 260 | G296: 701 | H296: 743 | I296: 658 | J296: 850 | K296: 675 | L296: 598 | M296: 540 | N296: 578 | O296: 717 | P296: 790 | Q296: 864 | R296: 680 | S296: 554 | T296: 962
A297: Majorna | B297: 104 | C297: 283 | D297: 998 | E297: 1117 | F297: 488 | G297: 1044 | H297: 1052 | I297: 1059 | J297: 919 | K297: 1009 | L297: 826 | M297: 635 | N297: 659 | O297: 1065 | P297: 1036 | Q297: 627 | R297: 452 | S297: 894 | T297: 532
A298: Pedagogen Park | B298: 107 | C298: 157 | D298: 405 | E298: 383 | F298: 186 | G298: 284 | H298: 373 | I298: 387 | J298: 557 | K298: 592 | L298: 450 | M298: 493 | N298: 564 | O298: 592 | P298: 635 | Q298: 863 | R298: 759 | S298: 476 | T298: 1053
A299: Åby | B299: 108 | C299: 279 | D299: 850 | E299: 772 | F299: 252 | G299: 685 | H299: 632 | I299: 788 | J299: 920 | K299: 900 | L299: 576 | M299: 490 | N299: 582 | O299: 844 | P299: 786 | Q299: 638 | R299: 474 | S299: 926 | T299: 488
A300: Avenyn | B300: 302 | C300: 1051 | D300: 930 | E300: 904 | F300: 752 | G300: 965 | H300: 1063 | I300: 1111 | J300: 809 | K300: 857 | L300: 1024 | M300: 646 | N300: 996 | O300: 1358 | P300: 1215 | Q300: 1093 | R300: 905 | S300: 885 | T300: 908
A301: Karlastaden | B301: 15 | C301: 0 | D301: 81 | E301: 105 | F301: 59 | G301: 199 | H301: 140 | I301: 142 | J301: 210 | K301: 185 | L301: 200 | M301: 159 | N301: 187 | O301: 208 | P301: 313 | Q301: 236 | R301: 245 | S301: 225 | T301: 244
C302: =SUM(C294:C301) -> 2527 | D302: =SUM(D294:D301) -> 5581 | E302: =SUM(E294:E301) -> 6059 | F302: =SUM(F294:F301) -> 2792 | G302: =SUM(G294:G301) -> 6004 | H302: =SUM(H294:H301) -> 6064 | I302: =SUM(I294:I301) -> 5954 | J302: =SUM(J294:J301) -> 6123 | ... T302: =SUM(T294:T301) -> 5971
A305: Teambesök / VGR | C305: 202409 | D305: 202410 | E305: 202411 | F305: 202412 | G305: 202501 | H305: 202502 | I305: 202503 | J305: 202504 | K305: 202505 | L305: 202506 | M305: 202507 | N305: 202508 | O305: 202509 | P305: 202510 | Q305: 202511 | R305: 202512 | S305: 202601 | T305: 202602
A306: Frölunda Torg | B306: 601 | C306: =44+15 -> 59 | D306: =65+16 -> 81 | E306: =45+14 -> 59 | F306: =45+4 -> 49 | G306: =37+15 -> 52 | H306: =33+13 -> 46 | I306: =24+11 -> 35 | J306: 41 | K306: 24 | L306: 24 | M306: 47 | N306: 6 | O306: 44 | P306: 46 | Q306: 49 | R306: 39 | S306: 23 | T306: 25
A307: Grimmered | B307: 602 | C307: =6+10 -> 16 | D307: =7+5 -> 12 | E307: =29+18 -> 47 | F307: =17+19 -> 36 | G307: =26+24 -> 50 | H307: =22+9 -> 31 | I307: =24+12 -> 36 | J307: 50 | K307: 26 | L307: 34 | M307: 28 | N307: 17 | O307: 57 | P307: 44 | Q307: 36 | R307: 29 | S307: 24 | T307: 26
...
